{"createdAt":"22/09/2021 10:08:08","results":[{"name":"TQM","price":"฿109.00","lossChance":"39.3%","linePercentage":"+86.49%","score":7.7,"factorPercentage":"80.80%","advice":"Sell","pe":41.76,"pbv":13.17,"dvdYield":"1.97%","industry":"Financials","sector":"Insurance","dividend":{"lastDate":"26/08/2021","predictedDate":"26/08/2022"}},{"name":"COM7","price":"฿71.00","lossChance":"39.7%","linePercentage":"+27.52%","score":7.46,"factorPercentage":"81.20%","advice":"Buy","pe":40.94,"pbv":22.41,"dvdYield":"1.41%","industry":"Services","sector":"Commerce","dividend":{"lastDate":"29/04/2021","predictedDate":"29/04/2022"}},{"name":"MEGA","price":"฿49.00","lossChance":"39.3%","linePercentage":"+201.02%","score":7.45,"factorPercentage":"81.80%","advice":"Buy","pe":26.58,"pbv":5.84,"dvdYield":"1.84%","industry":"Services","sector":"Commerce","dividend":{"lastDate":"27/08/2021","predictedDate":"27/08/2022"}},{"name":"BCH","price":"฿22.40","lossChance":"39.3%","linePercentage":"+107.14%","score":7.4,"factorPercentage":"80.80%","advice":"Buy","pe":25.85,"pbv":6.95,"dvdYield":"1.03%","industry":"Services","sector":"Health Care Services","dividend":{"lastDate":"31/08/2021","predictedDate":"31/08/2022"}},{"name":"HMPRO","price":"฿13.90","lossChance":"39.3%","linePercentage":"+91.42%","score":7.13,"factorPercentage":"74.20%","advice":"Neutral","pe":31.84,"pbv":8.4,"dvdYield":"2.16%","industry":"Services","sector":"Commerce","dividend":{"lastDate":"15/09/2021","predictedDate":"15/09/2022"}},{"name":"CHG","price":"฿3.82","lossChance":"39.3%","linePercentage":"+106.25%","score":7.09,"factorPercentage":"80.60%","advice":"Buy","pe":30.83,"pbv":9.29,"dvdYield":"1.31%","industry":"Services","sector":"Health Care Services","dividend":{"lastDate":"24/08/2021","predictedDate":"24/08/2022"}},{"name":"CBG","price":"฿127.00","lossChance":"43.2%","linePercentage":"+84.50%","score":6.93,"factorPercentage":"72.20%","advice":"Sell","pe":36.19,"pbv":12.84,"dvdYield":"1.89%","industry":"Agro & Food Industry","sector":"Food & Beverage","dividend":{"lastDate":"27/08/2021","predictedDate":"27/08/2022"}},{"name":"SAWAD","price":"฿68.50","lossChance":"40.9%","linePercentage":"-32.12%","score":6.84,"factorPercentage":"78.60%","advice":"Strong Sell","pe":18.96,"pbv":4.19,"dvdYield":"2.63%","industry":"Financials","sector":"Finance & Securities","dividend":{"lastDate":"05/05/2021","predictedDate":"05/05/2022"}},{"name":"MTC","price":"฿62.75","lossChance":"41.1%","linePercentage":"-5.04%","score":6.81,"factorPercentage":"70.20%","advice":"Buy","pe":24.85,"pbv":5.9,"dvdYield":"0.59%","industry":"Financials","sector":"Finance & Securities","dividend":{"lastDate":"29/04/2021","predictedDate":"29/04/2022"}},{"name":"OSP","price":"฿34.75","lossChance":"43.2%","linePercentage":"+214.23%","score":6.24,"factorPercentage":"69.40%","advice":"Sell","pe":29.01,"pbv":5.27,"dvdYield":"3.17%","industry":"Agro & Food Industry","sector":"Food & Beverage","dividend":{"lastDate":"24/08/2021","predictedDate":"24/08/2022"}},{"name":"GLOBAL","price":"฿20.90","lossChance":"43.2%","linePercentage":"+102.54%","score":6.18,"factorPercentage":"69.00%","advice":"Sell","pe":34.71,"pbv":5.31,"dvdYield":"0.85%","industry":"Services","sector":"Commerce","dividend":{"lastDate":"24/02/2021","predictedDate":"24/02/2022"}},{"name":"DELTA","price":"฿498.00","lossChance":"43.2%","linePercentage":"+1,000%","score":6.17,"factorPercentage":"70.20%","advice":"Sell","pe":81.35,"pbv":16.46,"dvdYield":"0.66%","industry":"Technology","sector":"Electronic Components","dividend":{"lastDate":"04/03/2021","predictedDate":"04/03/2022"}},{"name":"PTG","price":"฿17.40","lossChance":"40.9%","linePercentage":"-73.08%","score":6.14,"factorPercentage":"68.60%","advice":"Sell","pe":13.15,"pbv":3.59,"dvdYield":"2.87%","industry":"Resources","sector":"Energy & Utilities","dividend":{"lastDate":"11/03/2021","predictedDate":"11/03/2022"}},{"name":"PRM","price":"฿6.65","lossChance":"40.9%","linePercentage":"-46.27%","score":6.12,"factorPercentage":"68.00%","advice":"Sell","pe":10.19,"pbv":2.01,"dvdYield":"3.76%","industry":"Services","sector":"Transportation & Logistics","dividend":{"lastDate":"30/04/2021","predictedDate":"30/04/2022"}},{"name":"KTC","price":"฿63.00","lossChance":"43.2%","linePercentage":"+55.50%","score":6.07,"factorPercentage":"66.00%","advice":"Sell","pe":27.74,"pbv":6.71,"dvdYield":"1.40%","industry":"Financials","sector":"Finance & Securities","dividend":{"lastDate":"19/04/2021","predictedDate":"19/04/2022"}},{"name":"SYNEX","price":"฿24.60","lossChance":"46.9%","linePercentage":"+311.93%","score":6,"factorPercentage":"64.20%","advice":"Sell","pe":28.15,"pbv":5.8,"dvdYield":"2.20%","industry":"Technology","sector":"Information & Communication Technology","dividend":{"lastDate":"24/08/2021","predictedDate":"24/08/2022"}},{"name":"THANI","price":"฿4.20","lossChance":"42.3%","linePercentage":"-41.14%","score":5.92,"factorPercentage":"54.00%","advice":"Sell","pe":13.17,"pbv":2.22,"dvdYield":"4.05%","industry":"Financials","sector":"Finance & Securities","dividend":{"lastDate":"04/03/2021","predictedDate":"04/03/2022"}},{"name":"RS","price":"฿18.40","lossChance":"46.9%","linePercentage":"+287.75%","score":5.91,"factorPercentage":"59.00%","advice":"Sell","pe":41.26,"pbv":8.02,"dvdYield":"N.A.%","industry":"Services","sector":"Commerce","dividend":{"lastDate":"04/03/2020","predictedDate":"04/03/2021"}},{"name":"PTL","price":"฿28.00","lossChance":"43.8%","linePercentage":"+2.08%","score":5.89,"factorPercentage":"67.20%","advice":"Buy","pe":10.47,"pbv":1.53,"dvdYield":"3.57%","industry":"Industrials","sector":"Packaging","dividend":{"lastDate":"09/08/2021","predictedDate":"09/08/2022"}},{"name":"SCGP","price":"฿63.25","lossChance":"46.9%","linePercentage":"+259.05%","score":5.85,"factorPercentage":"60.80%","advice":"Neutral","pe":37.61,"pbv":2.91,"dvdYield":"0.71%","industry":"Industrials","sector":"Packaging","dividend":{"lastDate":"09/08/2021","predictedDate":"09/08/2022"}},{"name":"AEONTS","price":"฿202.00","lossChance":"43.9%","linePercentage":"-0.86%","score":5.76,"factorPercentage":"53.40%","advice":"Buy","pe":11.72,"pbv":2.78,"dvdYield":"2.23%","industry":"Financials","sector":"Finance & Securities","dividend":{"lastDate":"12/05/2021","predictedDate":"12/05/2022"}},{"name":"ORI","price":"฿10.20","lossChance":"43.9%","linePercentage":"-2.80%","score":5.74,"factorPercentage":"65.20%","advice":"Buy","pe":8.24,"pbv":2.07,"dvdYield":"4.80%","industry":"Property & Construction","sector":"Property Development","dividend":{"lastDate":"24/08/2021","predictedDate":"24/08/2022"}},{"name":"SCC","price":"฿410.00","lossChance":"44.2%","linePercentage":"+26.55%","score":5.7,"factorPercentage":"62.40%","advice":"Sell","pe":9.87,"pbv":1.4,"dvdYield":"3.41%","industry":"Property & Construction","sector":"Construction Materials","dividend":{"lastDate":"13/08/2021","predictedDate":"13/08/2022"}},{"name":"GPSC","price":"฿77.75","lossChance":"42.3%","linePercentage":"-36.12%","score":5.69,"factorPercentage":"48.40%","advice":"Neutral","pe":26.39,"pbv":2.1,"dvdYield":"1.93%","industry":"Resources","sector":"Energy & Utilities","dividend":{"lastDate":"08/09/2021","predictedDate":"08/09/2022"}},{"name":"ACE","price":"฿3.92","lossChance":"43.9%","linePercentage":"-3.01%","score":5.62,"factorPercentage":"61.60%","advice":"Neutral","pe":28.68,"pbv":3.18,"dvdYield":"1.22%","industry":"Resources","sector":"Energy & Utilities","dividend":{"lastDate":"11/03/2021","predictedDate":"11/03/2022"}},{"name":"TU","price":"฿22.20","lossChance":"43.8%","linePercentage":"+12.83%","score":5.61,"factorPercentage":"60.60%","advice":"Strong Buy","pe":13.49,"pbv":1.83,"dvdYield":"3.24%","industry":"Agro & Food Industry","sector":"Food & Beverage","dividend":{"lastDate":"23/08/2021","predictedDate":"23/08/2022"}},{"name":"EA","price":"฿64.00","lossChance":"43.8%","linePercentage":"+13.06%","score":5.61,"factorPercentage":"52.80%","advice":"Buy","pe":45.86,"pbv":8.15,"dvdYield":"0.47%","industry":"Resources","sector":"Energy & Utilities","dividend":{"lastDate":"12/03/2021","predictedDate":"12/03/2022"}},{"name":"CPF","price":"฿26.25","lossChance":"43.5%","linePercentage":"-11.50%","score":5.6,"factorPercentage":"58.00%","advice":"Sell","pe":8.64,"pbv":1.05,"dvdYield":"3.82%","industry":"Agro & Food Industry","sector":"Food & Beverage","dividend":{"lastDate":"30/08/2021","predictedDate":"30/08/2022"}},{"name":"TVO","price":"฿31.50","lossChance":"46.9%","linePercentage":"+68.37%","score":5.56,"factorPercentage":"76.80%","advice":"Strong Sell","pe":10.48,"pbv":2.52,"dvdYield":"5.40%","industry":"Agro & Food Industry","sector":"Food & Beverage","dividend":{"lastDate":"27/08/2021","predictedDate":"27/08/2022"}},{"name":"STGT","price":"฿32.50","lossChance":"42.3%","linePercentage":"-28.97%","score":5.49,"factorPercentage":"69.40%","advice":"Sell","pe":3.08,"pbv":2.41,"dvdYield":"8.06%","industry":"Consumer Products","sector":"Personal Products & Pharmaceuticals","dividend":{"lastDate":"23/08/2021","predictedDate":"23/08/2022"}},{"name":"SPALI","price":"฿20.60","lossChance":"46.9%","linePercentage":"+43.68%","score":5.48,"factorPercentage":"65.40%","advice":"Sell","pe":7.23,"pbv":1.05,"dvdYield":"4.85%","industry":"Property & Construction","sector":"Property Development","dividend":{"lastDate":"24/08/2021","predictedDate":"24/08/2022"}},{"name":"AP","price":"฿8.45","lossChance":"43.5%","linePercentage":"-15.41%","score":5.45,"factorPercentage":"64.00%","advice":"Buy","pe":5.41,"pbv":0.87,"dvdYield":"5.33%","industry":"Property & Construction","sector":"Property Development","dividend":{"lastDate":"11/05/2021","predictedDate":"11/05/2022"}},{"name":"TCAP","price":"฿34.00","lossChance":"44.2%","linePercentage":"+33.59%","score":5.38,"factorPercentage":"45.80%","advice":"Sell","pe":10.16,"pbv":0.56,"dvdYield":"8.82%","industry":"Financials","sector":"Banking","dividend":{"lastDate":"13/09/2021","predictedDate":"13/09/2022"}},{"name":"TISCO","price":"฿93.50","lossChance":"43.8%","linePercentage":"+5.62%","score":5.27,"factorPercentage":"55.60%","advice":"Strong Buy","pe":11.21,"pbv":1.98,"dvdYield":"6.74%","industry":"Financials","sector":"Banking","dividend":{"lastDate":"28/04/2021","predictedDate":"28/04/2022"}},{"name":"KBANK","price":"฿121.00","lossChance":"44.2%","linePercentage":"+41.07%","score":5.2,"factorPercentage":"58.40%","advice":"Buy","pe":7.27,"pbv":0.63,"dvdYield":"2.07%","industry":"Financials","sector":"Banking","dividend":{"lastDate":"08/09/2021","predictedDate":"08/09/2022"}},{"name":"ICHI","price":"฿11.20","lossChance":"46.9%","linePercentage":"+225.38%","score":5.19,"factorPercentage":"57.00%","advice":"Sell","pe":29.54,"pbv":2.46,"dvdYield":"4.46%","industry":"Agro & Food Industry","sector":"Food & Beverage","dividend":{"lastDate":"06/05/2021","predictedDate":"06/05/2022"}},{"name":"KCE","price":"฿81.75","lossChance":"46.9%","linePercentage":"+567.66%","score":5.19,"factorPercentage":"65.40%","advice":"Buy","pe":55.13,"pbv":7.57,"dvdYield":"0.97%","industry":"Technology","sector":"Electronic Components","dividend":{"lastDate":"23/08/2021","predictedDate":"23/08/2022"}},{"name":"ADVANC","price":"฿193.00","lossChance":"43.9%","linePercentage":"-5.86%","score":5.17,"factorPercentage":"50.80%","advice":"Buy","pe":20.98,"pbv":7.31,"dvdYield":"3.59%","industry":"Technology","sector":"Information & Communication Technology","dividend":{"lastDate":"16/08/2021","predictedDate":"16/08/2022"}},{"name":"BDMS","price":"฿22.90","lossChance":"46.9%","linePercentage":"+369.08%","score":5.16,"factorPercentage":"49.00%","advice":"Buy","pe":52.14,"pbv":4.43,"dvdYield":"2.40%","industry":"Services","sector":"Health Care Services","dividend":{"lastDate":"10/03/2021","predictedDate":"10/03/2022"}},{"name":"JMT","price":"฿49.25","lossChance":"49.4%","linePercentage":"+74.42%","score":4.92,"factorPercentage":"61.60%","advice":"Strong Buy","pe":46.39,"pbv":7.05,"dvdYield":"1.54%","industry":"Financials","sector":"Finance & Securities","dividend":{"lastDate":"23/08/2021","predictedDate":"23/08/2022"}},{"name":"RBF","price":"฿20.70","lossChance":"49.4%","linePercentage":"+1,000%","score":4.81,"factorPercentage":"49.60%","advice":"Strong Buy","pe":92.89,"pbv":10.39,"dvdYield":"0.72%","industry":"Agro & Food Industry","sector":"Food & Beverage","dividend":{"lastDate":"29/04/2021","predictedDate":"29/04/2022"}},{"name":"NRF","price":"฿8.70","lossChance":"49.4%","linePercentage":"+686.73%","score":4.72,"factorPercentage":"51.60%","advice":"Sell","pe":112.33,"pbv":4.68,"dvdYield":"0.05%","industry":"Agro & Food Industry","sector":"Food & Beverage","dividend":{"lastDate":"29/04/2021","predictedDate":"29/04/2022"}},{"name":"GULF","price":"฿40.75","lossChance":"49.4%","linePercentage":"+150.86%","score":4.71,"factorPercentage":"51.40%","advice":"Buy","pe":81.69,"pbv":6.91,"dvdYield":"0.93%","industry":"Resources","sector":"Energy & Utilities","dividend":{"lastDate":"05/03/2021","predictedDate":"05/03/2022"}},{"name":"PTTEP","price":"฿112.50","lossChance":"44.4%","linePercentage":"-25.50%","score":4.7,"factorPercentage":"43.40%","advice":"Buy","pe":15.73,"pbv":1.16,"dvdYield":"3.78%","industry":"Resources","sector":"Energy & Utilities","dividend":{"lastDate":"11/08/2021","predictedDate":"11/08/2022"}},{"name":"LH","price":"฿8.10","lossChance":"49.4%","linePercentage":"+111.31%","score":4.7,"factorPercentage":"54.80%","advice":"Buy","pe":12.07,"pbv":1.94,"dvdYield":"6.17%","industry":"Property & Construction","sector":"Property Development","dividend":{"lastDate":"24/08/2021","predictedDate":"24/08/2022"}},{"name":"BH","price":"฿139.50","lossChance":"49.4%","linePercentage":"+1,000%","score":4.68,"factorPercentage":"47.20%","advice":"Strong Buy","pe":158.11,"pbv":6.45,"dvdYield":"2.29%","industry":"Services","sector":"Health Care Services","dividend":{"lastDate":"26/08/2021","predictedDate":"26/08/2022"}},{"name":"STA","price":"฿33.75","lossChance":"43.0%","linePercentage":"-45.59%","score":4.65,"factorPercentage":"64.60%","advice":"Sell","pe":2.79,"pbv":1.15,"dvdYield":"6.67%","industry":"Agro & Food Industry","sector":"Agribusiness","dividend":{"lastDate":"23/08/2021","predictedDate":"23/08/2022"}},{"name":"CPALL","price":"฿64.25","lossChance":"49.4%","linePercentage":"+43.57%","score":4.65,"factorPercentage":"45.00%","advice":"Buy","pe":46.7,"pbv":6.15,"dvdYield":"1.40%","industry":"Services","sector":"Commerce","dividend":{"lastDate":"05/05/2021","predictedDate":"05/05/2022"}},{"name":"TTB","price":"฿1.07","lossChance":"45.2%","linePercentage":"-1.59%","score":4.59,"factorPercentage":"43.80%","advice":"Buy","pe":12.63,"pbv":0.5,"dvdYield":"4.21%","industry":"Financials","sector":"Banking","dividend":{"lastDate":"29/04/2021","predictedDate":"29/04/2022"}},{"name":"KKP","price":"฿54.50","lossChance":"49.4%","linePercentage":"+57.10%","score":4.54,"factorPercentage":"48.80%","advice":"Buy","pe":8.75,"pbv":0.96,"dvdYield":"4.13%","industry":"Financials","sector":"Banking","dividend":{"lastDate":"08/09/2021","predictedDate":"08/09/2022"}},{"name":"JMART","price":"฿43.75","lossChance":"49.4%","linePercentage":"+51.64%","score":4.48,"factorPercentage":"52.60%","advice":"Strong Buy","pe":41.14,"pbv":8.68,"dvdYield":"1.45%","industry":"Technology","sector":"Information & Communication Technology","dividend":{"lastDate":"23/08/2021","predictedDate":"23/08/2022"}},{"name":"CPN","price":"฿53.50","lossChance":"45.2%","linePercentage":"+42.64%","score":4.46,"factorPercentage":"45.40%","advice":"Strong Buy","pe":24.91,"pbv":3.36,"dvdYield":"1.31%","industry":"Property & Construction","sector":"Property Development","dividend":{"lastDate":"04/03/2021","predictedDate":"04/03/2022"}},{"name":"HANA","price":"฿82.00","lossChance":"49.4%","linePercentage":"+292.92%","score":4.42,"factorPercentage":"48.20%","advice":"Buy","pe":32.04,"pbv":2.9,"dvdYield":"1.71%","industry":"Technology","sector":"Electronic Components","dividend":{"lastDate":"11/03/2021","predictedDate":"11/03/2022"}},{"name":"OR","price":"฿28.25","lossChance":"49.4%","linePercentage":"+177.39%","score":4.41,"factorPercentage":"53.60%","advice":"Strong Sell","pe":24.93,"pbv":3.46,"dvdYield":"0.34%","industry":"Resources","sector":"Energy & Utilities","dividend":{"lastDate":"08/09/2021","predictedDate":"08/09/2022"}},{"name":"CKP","price":"฿5.35","lossChance":"49.4%","linePercentage":"+81.17%","score":4.35,"factorPercentage":"48.80%","advice":"Sell","pe":26.19,"pbv":1.83,"dvdYield":"0.65%","industry":"Resources","sector":"Energy & Utilities","dividend":{"lastDate":"28/04/2021","predictedDate":"28/04/2022"}},{"name":"BCPG","price":"฿14.00","lossChance":"44.0%","linePercentage":"-11.85%","score":4.34,"factorPercentage":"45.60%","advice":"Sell","pe":18.32,"pbv":1.58,"dvdYield":"2.02%","industry":"Resources","sector":"Energy & Utilities","dividend":{"lastDate":"07/09/2021","predictedDate":"07/09/2022"}},{"name":"IVL","price":"฿43.00","lossChance":"49.4%","linePercentage":"+53.88%","score":4.33,"factorPercentage":"51.20%","advice":"Buy","pe":15.05,"pbv":1.65,"dvdYield":"1.63%","industry":"Industrials","sector":"Petrochemicals & Chemicals","dividend":{"lastDate":"27/08/2021","predictedDate":"27/08/2022"}},{"name":"PTT","price":"฿39.50","lossChance":"45.2%","linePercentage":"+37.33%","score":4.28,"factorPercentage":"46.40%","advice":"Buy","pe":13.36,"pbv":1.16,"dvdYield":"2.53%","industry":"Resources","sector":"Energy & Utilities","dividend":{"lastDate":"29/09/2021","predictedDate":"29/09/2022"}},{"name":"KTB","price":"฿11.20","lossChance":"45.2%","linePercentage":"+25.92%","score":4.27,"factorPercentage":"40.20%","advice":"Buy","pe":8.65,"pbv":0.46,"dvdYield":"2.46%","industry":"Financials","sector":"Banking","dividend":{"lastDate":"21/04/2021","predictedDate":"21/04/2022"}},{"name":"TASCO","price":"฿18.00","lossChance":"43.0%","linePercentage":"-47.59%","score":4.25,"factorPercentage":"63.20%","advice":"Sell","pe":7.2,"pbv":1.95,"dvdYield":"8.89%","industry":"Property & Construction","sector":"Construction Materials","dividend":{"lastDate":"24/08/2021","predictedDate":"24/08/2022"}},{"name":"EGCO","price":"฿173.50","lossChance":"43.0%","linePercentage":"-37.78%","score":4.1,"factorPercentage":"37.00%","advice":"Sell","pe":14.81,"pbv":0.84,"dvdYield":"3.75%","industry":"Resources","sector":"Energy & Utilities","dividend":{"lastDate":"27/08/2021","predictedDate":"27/08/2022"}},{"name":"PLANB","price":"฿6.40","lossChance":"49.4%","linePercentage":"+190.76%","score":4.08,"factorPercentage":"44.60%","advice":"Buy","pe":230.87,"pbv":4.67,"dvdYield":"1.21%","industry":"Services","sector":"Media & Publishing","dividend":{"lastDate":"24/11/2020","predictedDate":"24/11/2021"}},{"name":"SINGER","price":"฿44.25","lossChance":"49.4%","linePercentage":"+355.53%","score":4.06,"factorPercentage":"50.60%","advice":"Strong Buy","pe":39.07,"pbv":6.07,"dvdYield":"0.52%","industry":"Services","sector":"Commerce","dividend":{"lastDate":"24/08/2021","predictedDate":"24/08/2022"}},{"name":"BGRIM","price":"฿41.75","lossChance":"44.7%","linePercentage":"-21.81%","score":4.05,"factorPercentage":"43.80%","advice":"Sell","pe":40.16,"pbv":3.78,"dvdYield":"1.08%","industry":"Resources","sector":"Energy & Utilities","dividend":{"lastDate":"26/08/2021","predictedDate":"26/08/2022"}},{"name":"BJC","price":"฿33.75","lossChance":"45.7%","linePercentage":"+24.61%","score":4.05,"factorPercentage":"32.80%","advice":"Sell","pe":31.82,"pbv":1.18,"dvdYield":"2.31%","industry":"Services","sector":"Commerce","dividend":{"lastDate":"24/08/2021","predictedDate":"24/08/2022"}},{"name":"BBL","price":"฿114.00","lossChance":"49.4%","linePercentage":"+74.34%","score":4.04,"factorPercentage":"42.40%","advice":"Buy","pe":11.05,"pbv":0.47,"dvdYield":"2.19%","industry":"Financials","sector":"Banking","dividend":{"lastDate":"08/09/2021","predictedDate":"08/09/2022"}},{"name":"SUPER","price":"฿0.97","lossChance":"43.8%","linePercentage":"-58.24%","score":3.95,"factorPercentage":"46.40%","advice":"Buy","pe":13.24,"pbv":1.4,"dvdYield":"0.62%","industry":"Resources","sector":"Energy & Utilities","dividend":{"lastDate":"10/05/2021","predictedDate":"10/05/2022"}},{"name":"BEM","price":"฿8.90","lossChance":"50.7%","linePercentage":"+325.85%","score":3.85,"factorPercentage":"35.60%","advice":"Strong Buy","pe":71.71,"pbv":3.6,"dvdYield":"1.12%","industry":"Services","sector":"Transportation & Logistics","dividend":{"lastDate":"07/05/2021","predictedDate":"07/05/2022"}},{"name":"DOHOME","price":"฿24.10","lossChance":"50.7%","linePercentage":"+201.65%","score":3.79,"factorPercentage":"54.00%","advice":"Sell","pe":37.72,"pbv":7.09,"dvdYield":"0.03%","industry":"Services","sector":"Commerce","dividend":{"lastDate":"03/03/2021","predictedDate":"03/03/2022"}},{"name":"PSL","price":"฿20.80","lossChance":"50.7%","linePercentage":"+391.08%","score":3.78,"factorPercentage":"49.40%","advice":"Sell","pe":26.88,"pbv":2.68,"dvdYield":"N.A.%","industry":"Services","sector":"Transportation & Logistics","dividend":{"lastDate":"27/08/2021","predictedDate":"27/08/2022"}},{"name":"STEC","price":"฿12.70","lossChance":"46.7%","linePercentage":"+15.71%","score":3.77,"factorPercentage":"43.40%","advice":"Sell","pe":21.48,"pbv":1.34,"dvdYield":"2.36%","industry":"Property & Construction","sector":"Construction Services","dividend":{"lastDate":"25/03/2021","predictedDate":"25/03/2022"}},{"name":"JAS","price":"฿2.82","lossChance":"50.7%","linePercentage":"+76.22%","score":3.77,"factorPercentage":"44.20%","advice":"Sell","pe":"","pbv":8.85,"dvdYield":"8.81%","industry":"Technology","sector":"Information & Communication Technology","dividend":{"lastDate":"03/12/2020","predictedDate":"03/12/2021"}},{"name":"QH","price":"฿2.24","lossChance":"50.7%","linePercentage":"+65.75%","score":3.75,"factorPercentage":"38.20%","advice":"Buy","pe":11.61,"pbv":0.9,"dvdYield":"5.36%","industry":"Property & Construction","sector":"Property Development","dividend":{"lastDate":"23/08/2021","predictedDate":"23/08/2022"}},{"name":"RATCH","price":"฿45.50","lossChance":"46.6%","linePercentage":"+35.27%","score":3.7,"factorPercentage":"50.00%","advice":"Sell","pe":8.18,"pbv":1,"dvdYield":"5.27%","industry":"Resources","sector":"Energy & Utilities","dividend":{"lastDate":"07/09/2021","predictedDate":"07/09/2022"}},{"name":"SCB","price":"฿107.50","lossChance":"50.7%","linePercentage":"+114.50%","score":3.69,"factorPercentage":"36.40%","advice":"Buy","pe":12.82,"pbv":0.87,"dvdYield":"2.14%","industry":"Financials","sector":"Banking","dividend":{"lastDate":"06/09/2021","predictedDate":"06/09/2022"}},{"name":"CRC","price":"฿33.50","lossChance":"50.7%","linePercentage":"+530.85%","score":3.69,"factorPercentage":"34.00%","advice":"Buy","pe":110.78,"pbv":3.73,"dvdYield":"1.19%","industry":"Services","sector":"Commerce","dividend":{"lastDate":"29/04/2021","predictedDate":"29/04/2022"}},{"name":"VGI","price":"฿6.35","lossChance":"50.7%","linePercentage":"+740.84%","score":3.69,"factorPercentage":"40.20%","advice":"Buy","pe":49.99,"pbv":3.44,"dvdYield":"0.96%","industry":"Services","sector":"Media & Publishing","dividend":{"lastDate":"15/07/2021","predictedDate":"15/07/2022"}},{"name":"INTUCH","price":"฿82.50","lossChance":"50.7%","linePercentage":"+314.45%","score":3.65,"factorPercentage":"51.60%","advice":"Buy","pe":24.49,"pbv":6.73,"dvdYield":"3.03%","industry":"Technology","sector":"Information & Communication Technology","dividend":{"lastDate":"17/08/2021","predictedDate":"17/08/2022"}},{"name":"AMATA","price":"฿18.60","lossChance":"45.7%","linePercentage":"-11.37%","score":3.52,"factorPercentage":"34.60%","advice":"Buy","pe":19.47,"pbv":1.28,"dvdYield":"1.57%","industry":"Property & Construction","sector":"Property Development","dividend":{"lastDate":"27/08/2021","predictedDate":"27/08/2022"}},{"name":"BANPU","price":"฿12.50","lossChance":"50.7%","linePercentage":"+195.76%","score":3.49,"factorPercentage":"44.80%","advice":"Buy","pe":45.08,"pbv":1.33,"dvdYield":"1.80%","industry":"Resources","sector":"Energy & Utilities","dividend":{"lastDate":"08/09/2021","predictedDate":"08/09/2022"}},{"name":"GUNKUL","price":"฿4.78","lossChance":"50.7%","linePercentage":"+159.16%","score":3.47,"factorPercentage":"37.60%","advice":"Buy","pe":11.1,"pbv":3.4,"dvdYield":"3.77%","industry":"Resources","sector":"Energy & Utilities","dividend":{"lastDate":"25/08/2021","predictedDate":"25/08/2022"}},{"name":"TRUE","price":"฿3.38","lossChance":"43.8%","linePercentage":"-34.04%","score":3.28,"factorPercentage":"33.40%","advice":"Buy","pe":"","pbv":1.38,"dvdYield":"2.07%","industry":"Technology","sector":"Information & Communication Technology","dividend":{"lastDate":"12/03/2021","predictedDate":"12/03/2022"}},{"name":"AOT","price":"฿62.25","lossChance":"50.7%","linePercentage":"+100.00%","score":3.14,"factorPercentage":"34.00%","advice":"Buy","pe":"","pbv":7.57,"dvdYield":"0.31%","industry":"Services","sector":"Transportation & Logistics","dividend":{"lastDate":"08/12/2020","predictedDate":"08/12/2021"}},{"name":"WHA","price":"฿3.24","lossChance":"50.7%","linePercentage":"+117.14%","score":3.08,"factorPercentage":"33.40%","advice":"Buy","pe":21.26,"pbv":1.68,"dvdYield":"3.09%","industry":"Property & Construction","sector":"Property Development","dividend":{"lastDate":"07/05/2021","predictedDate":"07/05/2022"}},{"name":"MAJOR","price":"฿21.90","lossChance":"53.4%","linePercentage":"+154.03%","score":2.98,"factorPercentage":"31.80%","advice":"Strong Buy","pe":"","pbv":3.18,"dvdYield":"N.A.%","industry":"Services","sector":"Media & Publishing","dividend":{"lastDate":"14/04/2020","predictedDate":"14/04/2021"}},{"name":"DTAC","price":"฿39.00","lossChance":"53.4%","linePercentage":"+312.12%","score":2.9,"factorPercentage":"29.40%","advice":"Buy","pe":22.69,"pbv":4.27,"dvdYield":"7.67%","industry":"Technology","sector":"Information & Communication Technology","dividend":{"lastDate":"30/07/2021","predictedDate":"30/07/2022"}},{"name":"PTTGC","price":"฿59.50","lossChance":"48.8%","linePercentage":"+19.00%","score":2.8,"factorPercentage":"53.60%","advice":"Sell","pe":6.37,"pbv":0.86,"dvdYield":"1.68%","industry":"Industrials","sector":"Petrochemicals & Chemicals","dividend":{"lastDate":"03/09/2021","predictedDate":"03/09/2022"}},{"name":"TKN","price":"฿6.90","lossChance":"53.4%","linePercentage":"+386.80%","score":2.8,"factorPercentage":"37.60%","advice":"Sell","pe":65.01,"pbv":4.85,"dvdYield":"3.04%","industry":"Agro & Food Industry","sector":"Food & Beverage","dividend":{"lastDate":"27/08/2021","predictedDate":"27/08/2022"}},{"name":"BEC","price":"฿12.70","lossChance":"53.4%","linePercentage":"+875.26%","score":2.8,"factorPercentage":"43.40%","advice":"Neutral","pe":39.01,"pbv":4.42,"dvdYield":"N.A.%","industry":"Services","sector":"Media & Publishing","dividend":{"lastDate":"22/08/2017","predictedDate":"22/08/2018"}},{"name":"CENTEL","price":"฿35.25","lossChance":"53.4%","linePercentage":"+1,000%","score":2.73,"factorPercentage":"29.00%","advice":"Strong Buy","pe":"","pbv":2.55,"dvdYield":"N.A.%","industry":"Services","sector":"Tourism & Leisure","dividend":{"lastDate":"03/05/2019","predictedDate":"03/05/2020"}},{"name":"BCP","price":"฿26.00","lossChance":"48.8%","linePercentage":"+24.19%","score":2.69,"factorPercentage":"35.80%","advice":"Neutral","pe":9.66,"pbv":0.69,"dvdYield":"1.54%","industry":"Resources","sector":"Energy & Utilities","dividend":{"lastDate":"08/09/2021","predictedDate":"08/09/2022"}},{"name":"BAM","price":"฿18.50","lossChance":"53.4%","linePercentage":"+258.45%","score":2.43,"factorPercentage":"28.20%","advice":"Neutral","pe":29.26,"pbv":1.45,"dvdYield":"2.77%","industry":"Financials","sector":"Finance & Securities","dividend":{"lastDate":"06/05/2021","predictedDate":"06/05/2022"}},{"name":"IRPC","price":"฿4.00","lossChance":"48.8%","linePercentage":"+18.77%","score":2.18,"factorPercentage":"46.20%","advice":"Buy","pe":6.14,"pbv":0.97,"dvdYield":"1.50%","industry":"Resources","sector":"Energy & Utilities","dividend":{"lastDate":"07/09/2021","predictedDate":"07/09/2022"}},{"name":"MINT","price":"฿32.25","lossChance":"56.6%","linePercentage":"+100.00%","score":1.96,"factorPercentage":"22.80%","advice":"Buy","pe":"","pbv":2.97,"dvdYield":"N.A.%","industry":"Agro & Food Industry","sector":"Food & Beverage","dividend":{"lastDate":"26/04/2019","predictedDate":"26/04/2020"}},{"name":"SPRC","price":"฿9.00","lossChance":"56.6%","linePercentage":"+126.72%","score":1.83,"factorPercentage":"45.20%","advice":"Buy","pe":9.98,"pbv":1.26,"dvdYield":"N.A.%","industry":"Resources","sector":"Energy & Utilities","dividend":{"lastDate":"05/03/2020","predictedDate":"05/03/2021"}},{"name":"CK","price":"฿20.00","lossChance":"56.6%","linePercentage":"+333.32%","score":1.81,"factorPercentage":"22.40%","advice":"Buy","pe":27.91,"pbv":1.29,"dvdYield":"1.00%","industry":"Property & Construction","sector":"Construction Services","dividend":{"lastDate":"10/05/2021","predictedDate":"10/05/2022"}},{"name":"BTS","price":"฿9.40","lossChance":"56.6%","linePercentage":"+193.38%","score":1.75,"factorPercentage":"22.40%","advice":"Buy","pe":22.43,"pbv":2.04,"dvdYield":"3.30%","industry":"Services","sector":"Transportation & Logistics","dividend":{"lastDate":"23/07/2021","predictedDate":"23/07/2022"}},{"name":"ESSO","price":"฿7.90","lossChance":"56.6%","linePercentage":"+123.31%","score":1.27,"factorPercentage":"40.20%","advice":"Sell","pe":6.01,"pbv":1.51,"dvdYield":"N.A.%","industry":"Resources","sector":"Energy & Utilities","dividend":{"lastDate":"02/05/2019","predictedDate":"02/05/2020"}},{"name":"TOP","price":"฿49.25","lossChance":"56.6%","linePercentage":"+153.40%","score":1.01,"factorPercentage":"31.20%","advice":"Sell","pe":7.47,"pbv":0.87,"dvdYield":"1.42%","industry":"Resources","sector":"Energy & Utilities","dividend":{"lastDate":"09/09/2021","predictedDate":"09/09/2022"}},{"name":"AAV","price":"฿2.76","lossChance":"58.5%","linePercentage":"+1,000%","score":0.01,"factorPercentage":"13.80%","advice":"Buy","pe":"","pbv":1.24,"dvdYield":"N.A.%","industry":"Services","sector":"Transportation & Logistics","dividend":{"lastDate":"25/09/2018","predictedDate":"25/09/2019"}}]}