{"createdAt":"20/07/2021 10:10:11","results":[{"name":"TNP","price":"฿5.25","lossChance":"40.1%","linePercentage":"+13.62%","score":7.82,"factorPercentage":"81.60%","advice":"","pe":26.36,"pbv":4.96,"dvdYield":"1.33%","industry":"Services","sector":"-","dividend":{"lastDate":"11/03/2021","predictedDate":"11/03/2022"}},{"name":"BOL","price":"฿9.55","lossChance":"39.0%","linePercentage":"+130.34%","score":7.44,"factorPercentage":"81.00%","advice":"","pe":41,"pbv":11.71,"dvdYield":"2.04%","industry":"Services","sector":"-","dividend":{"lastDate":"24/02/2021","predictedDate":"24/02/2022"}},{"name":"JUBILE","price":"฿24.00","lossChance":"40.7%","linePercentage":"-34.69%","score":7.38,"factorPercentage":"76.20%","advice":"","pe":14.77,"pbv":3.29,"dvdYield":"2.58%","industry":"Consumer Products","sector":"-","dividend":{"lastDate":"10/05/2021","predictedDate":"10/05/2022"}},{"name":"PIMO","price":"฿3.88","lossChance":"39.0%","linePercentage":"+296.73%","score":7.08,"factorPercentage":"75.20%","advice":"","pe":30.03,"pbv":4.5,"dvdYield":"1.34%","industry":"Industrial","sector":"-","dividend":{"lastDate":"05/05/2021","predictedDate":"05/05/2022"}},{"name":"YUASA","price":"฿17.60","lossChance":"43.0%","linePercentage":"+48.54%","score":6.96,"factorPercentage":"72.00%","advice":"","pe":11.73,"pbv":2.05,"dvdYield":"2.51%","industry":"Industrial","sector":"-","dividend":{"lastDate":"12/04/2021","predictedDate":"12/04/2022"}},{"name":"AUCT","price":"฿10.00","lossChance":"41.8%","linePercentage":"-5.81%","score":6.9,"factorPercentage":"75.80%","advice":"","pe":22.44,"pbv":9.56,"dvdYield":"4.10%","industry":"Services","sector":"-","dividend":{"lastDate":"20/04/2021","predictedDate":"20/04/2022"}},{"name":"XO","price":"฿20.60","lossChance":"43.0%","linePercentage":"+240.50%","score":6.87,"factorPercentage":"81.40%","advice":"","pe":23.27,"pbv":7.73,"dvdYield":"2.95%","industry":"Agro & Food Industry","sector":"-","dividend":{"lastDate":"09/03/2021","predictedDate":"09/03/2022"}},{"name":"MGT","price":"฿3.60","lossChance":"42.0%","linePercentage":"-20.40%","score":6.73,"factorPercentage":"76.00%","advice":"","pe":13.81,"pbv":2.85,"dvdYield":"2.78%","industry":"Industrial","sector":"-","dividend":{"lastDate":"05/05/2021","predictedDate":"05/05/2022"}},{"name":"TACC","price":"฿6.75","lossChance":"41.4%","linePercentage":"+36.62%","score":6.71,"factorPercentage":"71.40%","advice":"","pe":21.33,"pbv":5.33,"dvdYield":"4.44%","industry":"Agro & Food Industry","sector":"-","dividend":{"lastDate":"28/04/2021","predictedDate":"28/04/2022"}},{"name":"ICN","price":"฿4.98","lossChance":"41.8%","linePercentage":"-4.49%","score":6.43,"factorPercentage":"72.20%","advice":"","pe":16.02,"pbv":3.66,"dvdYield":"3.61%","industry":"Technology","sector":"-","dividend":{"lastDate":"10/03/2021","predictedDate":"10/03/2022"}},{"name":"KWM","price":"฿5.45","lossChance":"43.0%","linePercentage":"+374.57%","score":6.43,"factorPercentage":"70.80%","advice":"","pe":36.09,"pbv":5.88,"dvdYield":"1.32%","industry":"Industrial","sector":"-","dividend":{"lastDate":"06/05/2021","predictedDate":"06/05/2022"}},{"name":"NETBAY","price":"฿25.75","lossChance":"43.0%","linePercentage":"+43.48%","score":6.33,"factorPercentage":"61.40%","advice":"","pe":32.44,"pbv":10.08,"dvdYield":"3.04%","industry":"Technology","sector":"-","dividend":{"lastDate":"05/05/2021","predictedDate":"05/05/2022"}},{"name":"TPAC","price":"฿18.80","lossChance":"41.9%","linePercentage":"+4.83%","score":6.01,"factorPercentage":"66.20%","advice":"","pe":29.11,"pbv":2.85,"dvdYield":"1.55%","industry":"Industrial","sector":"-","dividend":{"lastDate":"07/05/2021","predictedDate":"07/05/2022"}},{"name":"TQR","price":"฿15.70","lossChance":"46.9%","linePercentage":"+252.60%","score":6,"factorPercentage":"72.80%","advice":"","pe":46.73,"pbv":8.73,"dvdYield":"0.09%","industry":"Financials","sector":"-","dividend":{"lastDate":"16/03/2021","predictedDate":"16/03/2022"}},{"name":"SPVI","price":"฿6.45","lossChance":"43.1%","linePercentage":"-18.67%","score":5.97,"factorPercentage":"66.80%","advice":"","pe":27.15,"pbv":5.78,"dvdYield":"1.71%","industry":"Technology","sector":"-","dividend":{"lastDate":"02/03/2021","predictedDate":"02/03/2022"}},{"name":"SELIC","price":"฿3.74","lossChance":"44.8%","linePercentage":"+32.61%","score":5.88,"factorPercentage":"58.60%","advice":"","pe":16.6,"pbv":2.91,"dvdYield":"1.28%","industry":"Industrial","sector":"-","dividend":{"lastDate":"29/04/2021","predictedDate":"29/04/2022"}},{"name":"VCOM","price":"฿6.25","lossChance":"44.8%","linePercentage":"+33.93%","score":5.82,"factorPercentage":"68.00%","advice":"","pe":20.96,"pbv":3.99,"dvdYield":"3.13%","industry":"Technology","sector":"-","dividend":{"lastDate":"05/03/2021","predictedDate":"05/03/2022"}},{"name":"AKP","price":"฿2.32","lossChance":"46.9%","linePercentage":"+120.43%","score":5.76,"factorPercentage":"63.40%","advice":"","pe":16.71,"pbv":1.65,"dvdYield":"0.99%","industry":"Services","sector":"-","dividend":{"lastDate":"06/05/2021","predictedDate":"06/05/2022"}},{"name":"PDG","price":"฿4.04","lossChance":"44.8%","linePercentage":"+41.60%","score":5.7,"factorPercentage":"59.20%","advice":"","pe":12.92,"pbv":1.71,"dvdYield":"7.92%","industry":"Industrial","sector":"-","dividend":{"lastDate":"15/03/2021","predictedDate":"15/03/2022"}},{"name":"TMILL","price":"฿3.62","lossChance":"46.9%","linePercentage":"+46.81%","score":5.69,"factorPercentage":"56.20%","advice":"","pe":13.25,"pbv":1.34,"dvdYield":"5.52%","industry":"Agro & Food Industry","sector":"-","dividend":{"lastDate":"23/03/2021","predictedDate":"23/03/2022"}},{"name":"DOD","price":"฿13.00","lossChance":"46.9%","linePercentage":"+98.90%","score":5.67,"factorPercentage":"68.80%","advice":"","pe":31.65,"pbv":4.2,"dvdYield":"N.A.%","industry":"Consumer Products","sector":"-","dividend":{"lastDate":"13/03/2020","predictedDate":"13/03/2021"}},{"name":"PHOL","price":"฿4.36","lossChance":"46.9%","linePercentage":"+112.44%","score":5.63,"factorPercentage":"65.80%","advice":"","pe":12.56,"pbv":2.49,"dvdYield":"6.65%","industry":"Services","sector":"-","dividend":{"lastDate":"03/03/2021","predictedDate":"03/03/2022"}},{"name":"YGG","price":"฿21.00","lossChance":"46.9%","linePercentage":"+354.43%","score":5.58,"factorPercentage":"66.00%","advice":"","pe":63.96,"pbv":10.01,"dvdYield":"0.83%","industry":"Services","sector":"-","dividend":{"lastDate":"27/05/2021","predictedDate":"27/05/2022"}},{"name":"KK","price":"฿3.32","lossChance":"46.9%","linePercentage":"+298.44%","score":5.56,"factorPercentage":"65.00%","advice":"","pe":37.38,"pbv":4.7,"dvdYield":"0.90%","industry":"Services","sector":"-","dividend":{"lastDate":"11/03/2021","predictedDate":"11/03/2022"}},{"name":"COLOR","price":"฿2.24","lossChance":"46.9%","linePercentage":"+98.56%","score":5.54,"factorPercentage":"55.60%","advice":"","pe":21,"pbv":1.66,"dvdYield":"2.23%","industry":"Industrial","sector":"-","dividend":{"lastDate":"07/05/2021","predictedDate":"07/05/2022"}},{"name":"TPLAS","price":"฿5.15","lossChance":"46.9%","linePercentage":"+85.82%","score":5.52,"factorPercentage":"62.80%","advice":"","pe":36.27,"pbv":4.33,"dvdYield":"1.94%","industry":"Industrial","sector":"-","dividend":{"lastDate":"22/04/2021","predictedDate":"22/04/2022"}},{"name":"UKEM","price":"฿3.36","lossChance":"46.9%","linePercentage":"+202.69%","score":5.51,"factorPercentage":"57.20%","advice":"","pe":35.19,"pbv":3.69,"dvdYield":"1.64%","industry":"Industrial","sector":"-","dividend":{"lastDate":"28/04/2021","predictedDate":"28/04/2022"}},{"name":"SFT","price":"฿6.40","lossChance":"46.9%","linePercentage":"+125.08%","score":5.45,"factorPercentage":"70.60%","advice":"","pe":31.66,"pbv":4.1,"dvdYield":"1.11%","industry":"Industrial","sector":"-","dividend":{"lastDate":"10/03/2021","predictedDate":"10/03/2022"}},{"name":"MBAX","price":"฿5.80","lossChance":"43.9%","linePercentage":"-5.38%","score":5.43,"factorPercentage":"68.40%","advice":"","pe":8.33,"pbv":1.9,"dvdYield":"15.17%","industry":"Industrial","sector":"-","dividend":{"lastDate":"21/04/2021","predictedDate":"21/04/2022"}},{"name":"UBIS","price":"฿6.95","lossChance":"46.9%","linePercentage":"+88.60%","score":5.39,"factorPercentage":"57.00%","advice":"","pe":14.78,"pbv":3.2,"dvdYield":"2.16%","industry":"Industrial","sector":"-","dividend":{"lastDate":"08/09/2020","predictedDate":"08/09/2021"}},{"name":"KUN","price":"฿2.86","lossChance":"44.2%","linePercentage":"+13.12%","score":5.3,"factorPercentage":"65.60%","advice":"","pe":19.52,"pbv":3.65,"dvdYield":"1.91%","industry":"Property & Construction","sector":"-","dividend":{"lastDate":"11/05/2021","predictedDate":"11/05/2022"}},{"name":"ATP30","price":"฿1.25","lossChance":"42.4%","linePercentage":"-26.35%","score":5.24,"factorPercentage":"45.60%","advice":"","pe":25.76,"pbv":1.72,"dvdYield":"2.40%","industry":"Services","sector":"-","dividend":{"lastDate":"08/04/2021","predictedDate":"08/04/2022"}},{"name":"SICT","price":"฿5.30","lossChance":"46.9%","linePercentage":"+831.98%","score":5.1,"factorPercentage":"59.80%","advice":"","pe":54.5,"pbv":5.8,"dvdYield":"0.81%","industry":"Technology","sector":"-","dividend":{"lastDate":"07/05/2021","predictedDate":"07/05/2022"}},{"name":"KUMWEL","price":"฿4.00","lossChance":"46.9%","linePercentage":"+393.85%","score":5.09,"factorPercentage":"55.40%","advice":"","pe":34.87,"pbv":3.34,"dvdYield":"2.25%","industry":"Industrial","sector":"-","dividend":{"lastDate":"06/05/2021","predictedDate":"06/05/2022"}},{"name":"SONIC","price":"฿5.00","lossChance":"46.9%","linePercentage":"+246.71%","score":5.08,"factorPercentage":"57.80%","advice":"","pe":31.51,"pbv":4.01,"dvdYield":"1.10%","industry":"Services","sector":"-","dividend":{"lastDate":"08/03/2021","predictedDate":"08/03/2022"}},{"name":"MOONG","price":"฿5.05","lossChance":"46.9%","linePercentage":"+96.58%","score":5.05,"factorPercentage":"52.00%","advice":"","pe":12.27,"pbv":1.04,"dvdYield":"3.56%","industry":"Consumer Products","sector":"-","dividend":{"lastDate":"07/05/2021","predictedDate":"07/05/2022"}},{"name":"TNH","price":"฿32.25","lossChance":"46.9%","linePercentage":"+236.05%","score":5.04,"factorPercentage":"48.40%","advice":"","pe":25.3,"pbv":2.87,"dvdYield":"1.40%","industry":"Services","sector":"-","dividend":{"lastDate":"27/11/2020","predictedDate":"27/11/2021"}},{"name":"ADD","price":"฿29.50","lossChance":"46.9%","linePercentage":"+478.41%","score":5.04,"factorPercentage":"60.00%","advice":"","pe":57.29,"pbv":"","dvdYield":"N.A.%","industry":"Services","sector":"-","dividend":{"lastDate":"-","predictedDate":"-"}},{"name":"ASN","price":"฿3.94","lossChance":"46.9%","linePercentage":"+65.70%","score":5.02,"factorPercentage":"42.60%","advice":"","pe":49.79,"pbv":2.49,"dvdYield":"0.23%","industry":"Financials","sector":"-","dividend":{"lastDate":"10/03/2021","predictedDate":"10/03/2022"}},{"name":"SAAM","price":"฿7.10","lossChance":"46.9%","linePercentage":"+1,000%","score":5,"factorPercentage":"50.00%","advice":"","pe":81.8,"pbv":7.05,"dvdYield":"0.89%","industry":"Resources","sector":"-","dividend":{"lastDate":"09/03/2021","predictedDate":"09/03/2022"}},{"name":"FSMART","price":"฿11.10","lossChance":"43.2%","linePercentage":"-41.87%","score":4.93,"factorPercentage":"52.20%","advice":"","pe":18.62,"pbv":6.63,"dvdYield":"5.41%","industry":"Services","sector":"-","dividend":{"lastDate":"09/03/2021","predictedDate":"09/03/2022"}},{"name":"APP","price":"฿3.48","lossChance":"49.2%","linePercentage":"+146.28%","score":4.92,"factorPercentage":"55.40%","advice":"","pe":21.03,"pbv":2.76,"dvdYield":"4.31%","industry":"Technology","sector":"-","dividend":{"lastDate":"27/04/2021","predictedDate":"27/04/2022"}},{"name":"STI","price":"฿7.20","lossChance":"45.9%","linePercentage":"-8.45%","score":4.91,"factorPercentage":"60.80%","advice":"","pe":11.9,"pbv":2.56,"dvdYield":"5.56%","industry":"Property & Construction","sector":"-","dividend":{"lastDate":"10/05/2021","predictedDate":"10/05/2022"}},{"name":"IIG","price":"฿26.00","lossChance":"49.2%","linePercentage":"+75.84%","score":4.88,"factorPercentage":"56.80%","advice":"","pe":40.71,"pbv":5.21,"dvdYield":"0.58%","industry":"Technology","sector":"-","dividend":{"lastDate":"06/05/2021","predictedDate":"06/05/2022"}},{"name":"BM","price":"฿3.88","lossChance":"49.2%","linePercentage":"+142.87%","score":4.88,"factorPercentage":"50.40%","advice":"","pe":29.09,"pbv":2.35,"dvdYield":"2.06%","industry":"Industrial","sector":"-","dividend":{"lastDate":"11/03/2021","predictedDate":"11/03/2022"}},{"name":"SMD","price":"฿13.00","lossChance":"49.2%","linePercentage":"+217.97%","score":4.86,"factorPercentage":"62.20%","advice":"","pe":31.63,"pbv":"","dvdYield":"N.A.%","industry":"Consumer Products","sector":"-","dividend":{"lastDate":"-","predictedDate":"-"}},{"name":"PROS","price":"฿3.00","lossChance":"49.2%","linePercentage":"+249.58%","score":4.84,"factorPercentage":"62.00%","advice":"","pe":23.22,"pbv":"","dvdYield":"N.A.%","industry":"Property & Construction","sector":"-","dividend":{"lastDate":"-","predictedDate":"-"}},{"name":"QTC","price":"฿5.00","lossChance":"45.9%","linePercentage":"+30.82%","score":4.79,"factorPercentage":"49.20%","advice":"","pe":11.46,"pbv":0.99,"dvdYield":"8.00%","industry":"Resources","sector":"-","dividend":{"lastDate":"30/04/2021","predictedDate":"30/04/2022"}},{"name":"A5","price":"฿1.50","lossChance":"50.5%","linePercentage":"+100.00%","score":4.77,"factorPercentage":"58.00%","advice":"","pe":"","pbv":"","dvdYield":"-%","industry":"Services","sector":"-","dividend":{"lastDate":"-","predictedDate":"-"}},{"name":"LEO","price":"฿11.10","lossChance":"49.2%","linePercentage":"+245.17%","score":4.77,"factorPercentage":"57.20%","advice":"","pe":47.63,"pbv":5.52,"dvdYield":"0.63%","industry":"Services","sector":"-","dividend":{"lastDate":"10/05/2021","predictedDate":"10/05/2022"}},{"name":"TMI","price":"฿1.32","lossChance":"49.2%","linePercentage":"+520.26%","score":4.77,"factorPercentage":"50.60%","advice":"","pe":46.01,"pbv":4.51,"dvdYield":"N.A.%","industry":"Industrial","sector":"-","dividend":{"lastDate":"03/03/2017","predictedDate":"03/03/2018"}},{"name":"ARROW","price":"฿8.20","lossChance":"44.7%","linePercentage":"-9.82%","score":4.66,"factorPercentage":"53.60%","advice":"","pe":14.05,"pbv":1.63,"dvdYield":"6.10%","industry":"Property & Construction","sector":"-","dividend":{"lastDate":"10/05/2021","predictedDate":"10/05/2022"}},{"name":"PJW","price":"฿4.68","lossChance":"49.2%","linePercentage":"+252.81%","score":4.63,"factorPercentage":"54.20%","advice":"","pe":21.75,"pbv":2.33,"dvdYield":"2.67%","industry":"Industrial","sector":"-","dividend":{"lastDate":"12/04/2021","predictedDate":"12/04/2022"}},{"name":"WINNER","price":"฿3.52","lossChance":"49.2%","linePercentage":"+119.06%","score":4.62,"factorPercentage":"46.20%","advice":"","pe":19.68,"pbv":2.2,"dvdYield":"5.68%","industry":"Services","sector":"-","dividend":{"lastDate":"11/03/2021","predictedDate":"11/03/2022"}},{"name":"SWC","price":"฿5.95","lossChance":"49.2%","linePercentage":"+153.25%","score":4.61,"factorPercentage":"53.80%","advice":"","pe":25.77,"pbv":2.9,"dvdYield":"6.23%","industry":"Industrial","sector":"-","dividend":{"lastDate":"06/05/2021","predictedDate":"06/05/2022"}},{"name":"MITSIB","price":"฿1.33","lossChance":"49.2%","linePercentage":"+83.88%","score":4.54,"factorPercentage":"42.80%","advice":"","pe":98.8,"pbv":1.34,"dvdYield":"3.31%","industry":"Financials","sector":"-","dividend":{"lastDate":"06/05/2021","predictedDate":"06/05/2022"}},{"name":"NDR","price":"฿3.52","lossChance":"49.2%","linePercentage":"+251.12%","score":4.54,"factorPercentage":"53.40%","advice":"","pe":20.34,"pbv":1.56,"dvdYield":"1.33%","industry":"Industrial","sector":"-","dividend":{"lastDate":"11/03/2021","predictedDate":"11/03/2022"}},{"name":"ADB","price":"฿2.36","lossChance":"49.2%","linePercentage":"+112.80%","score":4.52,"factorPercentage":"56.20%","advice":"","pe":18.28,"pbv":2.32,"dvdYield":"2.33%","industry":"Industrial","sector":"-","dividend":{"lastDate":"28/04/2021","predictedDate":"28/04/2022"}},{"name":"AMA","price":"฿5.65","lossChance":"43.2%","linePercentage":"-55.03%","score":4.51,"factorPercentage":"44.80%","advice":"","pe":16.87,"pbv":1.33,"dvdYield":"3.54%","industry":"Services","sector":"-","dividend":{"lastDate":"08/03/2021","predictedDate":"08/03/2022"}},{"name":"ABICO","price":"฿5.25","lossChance":"49.2%","linePercentage":"+96.26%","score":4.49,"factorPercentage":"47.20%","advice":"","pe":29.03,"pbv":1.35,"dvdYield":"0.08%","industry":"Agro & Food Industry","sector":"-","dividend":{"lastDate":"29/04/2021","predictedDate":"29/04/2022"}},{"name":"TAKUNI","price":"฿1.25","lossChance":"45.9%","linePercentage":"+31.60%","score":4.47,"factorPercentage":"41.60%","advice":"","pe":30.58,"pbv":1.11,"dvdYield":"3.00%","industry":"Resources","sector":"-","dividend":{"lastDate":"17/03/2021","predictedDate":"17/03/2022"}},{"name":"HARN","price":"฿2.54","lossChance":"45.9%","linePercentage":"+29.12%","score":4.46,"factorPercentage":"42.00%","advice":"","pe":16.63,"pbv":1.11,"dvdYield":"5.12%","industry":"Services","sector":"-","dividend":{"lastDate":"12/03/2021","predictedDate":"12/03/2022"}},{"name":"INSET","price":"฿6.50","lossChance":"45.9%","linePercentage":"+41.11%","score":4.46,"factorPercentage":"53.40%","advice":"","pe":28.95,"pbv":4.65,"dvdYield":"1.66%","industry":"Technology","sector":"-","dividend":{"lastDate":"28/04/2021","predictedDate":"28/04/2022"}},{"name":"DITTO","price":"฿16.20","lossChance":"49.2%","linePercentage":"+970.36%","score":4.46,"factorPercentage":"57.60%","advice":"","pe":58.12,"pbv":"","dvdYield":"N.A.%","industry":"Technology","sector":"-","dividend":{"lastDate":"-","predictedDate":"-"}},{"name":"IP","price":"฿23.90","lossChance":"49.2%","linePercentage":"+660.99%","score":4.42,"factorPercentage":"52.00%","advice":"","pe":117.65,"pbv":14.07,"dvdYield":"0.07%","industry":"Consumer Products","sector":"-","dividend":{"lastDate":"11/03/2021","predictedDate":"11/03/2022"}},{"name":"PACO","price":"฿2.88","lossChance":"49.2%","linePercentage":"+309.29%","score":4.38,"factorPercentage":"46.80%","advice":"","pe":37.43,"pbv":3.38,"dvdYield":"N.A.%","industry":"Industrial","sector":"-","dividend":{"lastDate":"-","predictedDate":"-"}},{"name":"TM","price":"฿4.04","lossChance":"49.2%","linePercentage":"+64.60%","score":4.36,"factorPercentage":"42.40%","advice":"","pe":42.93,"pbv":2.78,"dvdYield":"2.48%","industry":"Consumer Products","sector":"-","dividend":{"lastDate":"26/04/2021","predictedDate":"26/04/2022"}},{"name":"FPI","price":"฿2.44","lossChance":"49.2%","linePercentage":"+135.38%","score":4.33,"factorPercentage":"48.20%","advice":"","pe":30.62,"pbv":2.17,"dvdYield":"1.64%","industry":"Industrial","sector":"-","dividend":{"lastDate":"06/05/2021","predictedDate":"06/05/2022"}},{"name":"FLOYD","price":"฿1.85","lossChance":"49.2%","linePercentage":"+525.29%","score":4.23,"factorPercentage":"55.60%","advice":"","pe":36.39,"pbv":1.62,"dvdYield":"N.A.%","industry":"Property & Construction","sector":"-","dividend":{"lastDate":"09/04/2020","predictedDate":"09/04/2021"}},{"name":"ETE","price":"฿2.32","lossChance":"49.2%","linePercentage":"+46.79%","score":4.16,"factorPercentage":"48.40%","advice":"","pe":22.92,"pbv":1.45,"dvdYield":"1.61%","industry":"Services","sector":"-","dividend":{"lastDate":"11/03/2021","predictedDate":"11/03/2022"}},{"name":"TPS","price":"฿2.30","lossChance":"49.2%","linePercentage":"+142.98%","score":4.16,"factorPercentage":"50.40%","advice":"","pe":17.15,"pbv":2.03,"dvdYield":"1.45%","industry":"Technology","sector":"-","dividend":{"lastDate":"05/04/2021","predictedDate":"05/04/2022"}},{"name":"TNDT","price":"฿2.72","lossChance":"49.2%","linePercentage":"+120.96%","score":4.15,"factorPercentage":"44.80%","advice":"","pe":34.99,"pbv":1.18,"dvdYield":"N.A.%","industry":"Services","sector":"-","dividend":{"lastDate":"10/03/2017","predictedDate":"10/03/2018"}},{"name":"TPCH","price":"฿11.60","lossChance":"43.2%","linePercentage":"-37.98%","score":4.14,"factorPercentage":"39.20%","advice":"","pe":21.88,"pbv":1.54,"dvdYield":"1.71%","industry":"Resources","sector":"-","dividend":{"lastDate":"06/05/2021","predictedDate":"06/05/2022"}},{"name":"ZIGA","price":"฿5.00","lossChance":"49.2%","linePercentage":"+184.28%","score":4.13,"factorPercentage":"59.80%","advice":"","pe":18.03,"pbv":3.23,"dvdYield":"3.22%","industry":"Industrial","sector":"-","dividend":{"lastDate":"04/03/2021","predictedDate":"04/03/2022"}},{"name":"AU","price":"฿10.20","lossChance":"49.2%","linePercentage":"+123.38%","score":4.07,"factorPercentage":"41.20%","advice":"","pe":154.28,"pbv":9.64,"dvdYield":"0.59%","industry":"Agro & Food Industry","sector":"-","dividend":{"lastDate":"07/05/2021","predictedDate":"07/05/2022"}},{"name":"SE","price":"฿1.17","lossChance":"43.2%","linePercentage":"-43.43%","score":4.06,"factorPercentage":"43.40%","advice":"","pe":22.37,"pbv":1.98,"dvdYield":"0.18%","industry":"Services","sector":"-","dividend":{"lastDate":"12/03/2021","predictedDate":"12/03/2022"}},{"name":"OCEAN","price":"฿1.68","lossChance":"49.2%","linePercentage":"+400.71%","score":4.05,"factorPercentage":"49.80%","advice":"","pe":31.89,"pbv":3.7,"dvdYield":"N.A.%","industry":"Consumer Products","sector":"-","dividend":{"lastDate":"23/08/2016","predictedDate":"23/08/2017"}},{"name":"SECURE","price":"฿26.25","lossChance":"49.2%","linePercentage":"+993.71%","score":4.04,"factorPercentage":"58.00%","advice":"","pe":57.86,"pbv":"","dvdYield":"N.A.%","industry":"Technology","sector":"-","dividend":{"lastDate":"-","predictedDate":"-"}},{"name":"ARIP","price":"฿1.02","lossChance":"50.9%","linePercentage":"+798.81%","score":3.91,"factorPercentage":"52.00%","advice":"","pe":134.21,"pbv":2.28,"dvdYield":"N.A.%","industry":"Services","sector":"-","dividend":{"lastDate":"-","predictedDate":"-"}},{"name":"PLANET","price":"฿2.80","lossChance":"50.9%","linePercentage":"+357.33%","score":3.89,"factorPercentage":"42.80%","advice":"","pe":59.55,"pbv":2.53,"dvdYield":"N.A.%","industry":"Technology","sector":"-","dividend":{"lastDate":"-","predictedDate":"-"}},{"name":"PROEN","price":"฿6.60","lossChance":"50.9%","linePercentage":"+775.62%","score":3.87,"factorPercentage":"51.20%","advice":"","pe":70.06,"pbv":"","dvdYield":"N.A.%","industry":"Technology","sector":"-","dividend":{"lastDate":"25/05/2021","predictedDate":"25/05/2022"}},{"name":"NBC","price":"฿0.78","lossChance":"46.1%","linePercentage":"-28.05%","score":3.85,"factorPercentage":"49.20%","advice":"","pe":22.98,"pbv":1.26,"dvdYield":"N.A.%","industry":"Services","sector":"-","dividend":{"lastDate":"-","predictedDate":"-"}},{"name":"AF","price":"฿0.73","lossChance":"50.9%","linePercentage":"+339.83%","score":3.77,"factorPercentage":"39.80%","advice":"","pe":24.32,"pbv":2.18,"dvdYield":"2.88%","industry":"Financials","sector":"-","dividend":{"lastDate":"29/12/2020","predictedDate":"29/12/2021"}},{"name":"TVD","price":"฿1.13","lossChance":"50.9%","linePercentage":"+289.42%","score":3.76,"factorPercentage":"38.60%","advice":"","pe":145.77,"pbv":1.56,"dvdYield":"3.78%","industry":"Services","sector":"-","dividend":{"lastDate":"26/11/2020","predictedDate":"26/11/2021"}},{"name":"TMW","price":"฿35.00","lossChance":"44.2%","linePercentage":"-40.98%","score":3.71,"factorPercentage":"35.00%","advice":"","pe":22.96,"pbv":0.57,"dvdYield":"1.31%","industry":"Industrial","sector":"-","dividend":{"lastDate":"04/08/2021","predictedDate":"04/08/2022"}},{"name":"CPR","price":"฿4.44","lossChance":"50.9%","linePercentage":"+191.46%","score":3.59,"factorPercentage":"38.20%","advice":"","pe":25.37,"pbv":1.57,"dvdYield":"1.80%","industry":"Industrial","sector":"-","dividend":{"lastDate":"10/05/2021","predictedDate":"10/05/2022"}},{"name":"BIZ","price":"฿9.80","lossChance":"50.9%","linePercentage":"+362.46%","score":3.59,"factorPercentage":"52.20%","advice":"","pe":35.35,"pbv":6.39,"dvdYield":"1.53%","industry":"Consumer Products","sector":"-","dividend":{"lastDate":"09/03/2021","predictedDate":"09/03/2022"}},{"name":"CMC","price":"฿1.36","lossChance":"50.9%","linePercentage":"+122.69%","score":3.57,"factorPercentage":"41.00%","advice":"","pe":13.78,"pbv":0.52,"dvdYield":"0.23%","industry":"Property & Construction","sector":"-","dividend":{"lastDate":"12/03/2021","predictedDate":"12/03/2022"}},{"name":"CAZ","price":"฿2.52","lossChance":"44.2%","linePercentage":"-51.07%","score":3.51,"factorPercentage":"44.00%","advice":"","pe":12.27,"pbv":1.36,"dvdYield":"0.86%","industry":"Property & Construction","sector":"-","dividend":{"lastDate":"17/03/2021","predictedDate":"17/03/2022"}},{"name":"NPK","price":"฿14.50","lossChance":"50.9%","linePercentage":"+46.94%","score":3.49,"factorPercentage":"40.60%","advice":"","pe":22.59,"pbv":0.33,"dvdYield":"0.69%","industry":"Consumer Products","sector":"-","dividend":{"lastDate":"07/05/2021","predictedDate":"07/05/2022"}},{"name":"VL","price":"฿2.18","lossChance":"47.3%","linePercentage":"-1.27%","score":3.38,"factorPercentage":"28.40%","advice":"","pe":28.81,"pbv":2.07,"dvdYield":"3.21%","industry":"Services","sector":"-","dividend":{"lastDate":"10/03/2021","predictedDate":"10/03/2022"}},{"name":"EFORL","price":"฿0.13","lossChance":"47.5%","linePercentage":"+37.27%","score":3.37,"factorPercentage":"53.40%","advice":"","pe":39.17,"pbv":6.14,"dvdYield":"N.A.%","industry":"Consumer Products","sector":"-","dividend":{"lastDate":"-","predictedDate":"-"}},{"name":"DHOUSE","price":"฿1.21","lossChance":"50.9%","linePercentage":"+266.40%","score":3.37,"factorPercentage":"32.80%","advice":"","pe":99.47,"pbv":2.11,"dvdYield":"2.48%","industry":"Property & Construction","sector":"-","dividend":{"lastDate":"23/03/2021","predictedDate":"23/03/2022"}},{"name":"AIE","price":"฿1.38","lossChance":"50.9%","linePercentage":"+73.80%","score":3.35,"factorPercentage":"56.40%","advice":"","pe":15.46,"pbv":3.16,"dvdYield":"3.62%","industry":"Resources","sector":"-","dividend":{"lastDate":"12/04/2021","predictedDate":"12/04/2022"}},{"name":"LDC","price":"฿1.33","lossChance":"50.9%","linePercentage":"+79.11%","score":3.35,"factorPercentage":"41.40%","advice":"","pe":"","pbv":3.52,"dvdYield":"N.A.%","industry":"Services","sector":"-","dividend":{"lastDate":"-","predictedDate":"-"}},{"name":"SK","price":"฿1.29","lossChance":"50.9%","linePercentage":"+135.75%","score":3.26,"factorPercentage":"38.00%","advice":"","pe":25.71,"pbv":1.72,"dvdYield":"1.55%","industry":"Property & Construction","sector":"-","dividend":{"lastDate":"11/05/2021","predictedDate":"11/05/2022"}},{"name":"IND","price":"฿1.89","lossChance":"50.9%","linePercentage":"+293.51%","score":3.26,"factorPercentage":"45.60%","advice":"","pe":52.87,"pbv":1.88,"dvdYield":"N.A.%","industry":"Property & Construction","sector":"-","dividend":{"lastDate":"-","predictedDate":"-"}},{"name":"TRT","price":"฿2.16","lossChance":"46.1%","linePercentage":"-26.40%","score":3.24,"factorPercentage":"40.80%","advice":"","pe":17.76,"pbv":0.63,"dvdYield":"0.93%","industry":"Resources","sector":"-","dividend":{"lastDate":"11/05/2021","predictedDate":"11/05/2022"}},{"name":"AIRA","price":"฿2.02","lossChance":"50.9%","linePercentage":"+1,000%","score":3.23,"factorPercentage":"40.80%","advice":"","pe":347.32,"pbv":3.46,"dvdYield":"0.64%","industry":"Financials","sector":"-","dividend":{"lastDate":"10/03/2021","predictedDate":"10/03/2022"}},{"name":"MUD","price":"฿2.02","lossChance":"50.9%","linePercentage":"+231.81%","score":3.21,"factorPercentage":"29.60%","advice":"","pe":"","pbv":0.95,"dvdYield":"N.A.%","industry":"Agro & Food Industry","sector":"-","dividend":{"lastDate":"05/05/2020","predictedDate":"05/05/2021"}},{"name":"SALEE","price":"฿1.29","lossChance":"50.9%","linePercentage":"+1,000%","score":3.2,"factorPercentage":"42.60%","advice":"","pe":311.34,"pbv":1.62,"dvdYield":"N.A.%","industry":"Industrial","sector":"-","dividend":{"lastDate":"02/05/2019","predictedDate":"02/05/2020"}},{"name":"ABM","price":"฿1.49","lossChance":"47.5%","linePercentage":"+35.89%","score":3.2,"factorPercentage":"37.80%","advice":"","pe":51.01,"pbv":1.26,"dvdYield":"N.A.%","industry":"Resources","sector":"-","dividend":{"lastDate":"-","predictedDate":"-"}},{"name":"ALL","price":"฿3.08","lossChance":"47.5%","linePercentage":"+37.13%","score":3.16,"factorPercentage":"36.20%","advice":"","pe":36.3,"pbv":0.97,"dvdYield":"1.35%","industry":"Property & Construction","sector":"-","dividend":{"lastDate":"26/01/2021","predictedDate":"26/01/2022"}},{"name":"ITEL","price":"฿4.20","lossChance":"44.2%","linePercentage":"-59.48%","score":3.15,"factorPercentage":"39.40%","advice":"","pe":22.85,"pbv":2.22,"dvdYield":"N.A.%","industry":"Technology","sector":"-","dividend":{"lastDate":"07/05/2019","predictedDate":"07/05/2020"}},{"name":"STC","price":"฿0.82","lossChance":"47.5%","linePercentage":"+33.09%","score":3.14,"factorPercentage":"29.60%","advice":"","pe":57.45,"pbv":1.23,"dvdYield":"1.95%","industry":"Property & Construction","sector":"-","dividend":{"lastDate":"11/03/2021","predictedDate":"11/03/2022"}},{"name":"PRAPAT","price":"฿1.74","lossChance":"50.9%","linePercentage":"+274.89%","score":3.1,"factorPercentage":"30.40%","advice":"","pe":"","pbv":1.24,"dvdYield":"1.15%","industry":"Industrial","sector":"-","dividend":{"lastDate":"05/05/2021","predictedDate":"05/05/2022"}},{"name":"PICO","price":"฿3.10","lossChance":"50.9%","linePercentage":"+100.00%","score":3.08,"factorPercentage":"31.60%","advice":"","pe":"","pbv":1.89,"dvdYield":"N.A.%","industry":"Services","sector":"-","dividend":{"lastDate":"28/02/2020","predictedDate":"28/02/2021"}},{"name":"FVC","price":"฿0.94","lossChance":"50.9%","linePercentage":"+100.00%","score":3.06,"factorPercentage":"36.20%","advice":"","pe":"","pbv":1.68,"dvdYield":"N.A.%","industry":"Services","sector":"-","dividend":{"lastDate":"03/05/2019","predictedDate":"03/05/2020"}},{"name":"PPM","price":"฿1.88","lossChance":"50.9%","linePercentage":"+953.64%","score":3.06,"factorPercentage":"38.20%","advice":"","pe":40.36,"pbv":0.91,"dvdYield":"0.80%","industry":"Industrial","sector":"-","dividend":{"lastDate":"10/05/2021","predictedDate":"10/05/2022"}},{"name":"SMART","price":"฿0.86","lossChance":"47.5%","linePercentage":"+22.27%","score":3.05,"factorPercentage":"38.00%","advice":"","pe":16.55,"pbv":1.5,"dvdYield":"4.07%","industry":"Property & Construction","sector":"-","dividend":{"lastDate":"10/05/2021","predictedDate":"10/05/2022"}},{"name":"D","price":"฿3.88","lossChance":"50.9%","linePercentage":"+1,000%","score":3.05,"factorPercentage":"38.00%","advice":"","pe":531.97,"pbv":2.35,"dvdYield":"0.24%","industry":"Services","sector":"-","dividend":{"lastDate":"06/05/2021","predictedDate":"06/05/2022"}},{"name":"KOOL","price":"฿0.87","lossChance":"47.5%","linePercentage":"+26.44%","score":3.04,"factorPercentage":"34.00%","advice":"","pe":"","pbv":3.46,"dvdYield":"N.A.%","industry":"Services","sector":"-","dividend":{"lastDate":"27/04/2017","predictedDate":"27/04/2018"}},{"name":"TVT","price":"฿0.69","lossChance":"50.9%","linePercentage":"+1,000%","score":3.03,"factorPercentage":"35.00%","advice":"","pe":"","pbv":0.9,"dvdYield":"N.A.%","industry":"Services","sector":"-","dividend":{"lastDate":"02/05/2019","predictedDate":"02/05/2020"}},{"name":"ECF","price":"฿1.75","lossChance":"50.9%","linePercentage":"+274.99%","score":3.02,"factorPercentage":"34.80%","advice":"","pe":43.77,"pbv":1.33,"dvdYield":"0.71%","industry":"Consumer Products","sector":"-","dividend":{"lastDate":"29/04/2021","predictedDate":"29/04/2022"}},{"name":"TITLE","price":"฿2.24","lossChance":"50.9%","linePercentage":"+100.00%","score":3,"factorPercentage":"29.80%","advice":"","pe":"","pbv":2.5,"dvdYield":"N.A.%","industry":"Property & Construction","sector":"-","dividend":{"lastDate":"04/03/2020","predictedDate":"04/03/2021"}},{"name":"TAPAC","price":"฿4.22","lossChance":"50.9%","linePercentage":"+465.73%","score":3,"factorPercentage":"35.80%","advice":"","pe":"","pbv":1.72,"dvdYield":"0.24%","industry":"Property & Construction","sector":"-","dividend":{"lastDate":"04/02/2021","predictedDate":"04/02/2022"}},{"name":"SPA","price":"฿7.05","lossChance":"53.4%","linePercentage":"+100.00%","score":2.86,"factorPercentage":"30.60%","advice":"","pe":"","pbv":7.27,"dvdYield":"N.A.%","industry":"Services","sector":"-","dividend":{"lastDate":"12/05/2020","predictedDate":"12/05/2021"}},{"name":"BROOK","price":"฿0.61","lossChance":"53.4%","linePercentage":"+96.46%","score":2.83,"factorPercentage":"42.60%","advice":"","pe":9.05,"pbv":1.91,"dvdYield":"6.62%","industry":"Financials","sector":"-","dividend":{"lastDate":"10/03/2021","predictedDate":"10/03/2022"}},{"name":"WINMED","price":"฿6.90","lossChance":"53.4%","linePercentage":"+696.86%","score":2.83,"factorPercentage":"40.80%","advice":"","pe":52.47,"pbv":"","dvdYield":"N.A.%","industry":"Consumer Products","sector":"-","dividend":{"lastDate":"-","predictedDate":"-"}},{"name":"NCL","price":"฿3.82","lossChance":"53.4%","linePercentage":"+1,000%","score":2.79,"factorPercentage":"26.40%","advice":"","pe":"","pbv":6.17,"dvdYield":"N.A.%","industry":"Services","sector":"-","dividend":{"lastDate":"07/05/2019","predictedDate":"07/05/2020"}},{"name":"SANKO","price":"฿1.46","lossChance":"53.4%","linePercentage":"+100.00%","score":2.77,"factorPercentage":"30.80%","advice":"","pe":"","pbv":2.56,"dvdYield":"N.A.%","industry":"Industrial","sector":"-","dividend":{"lastDate":"19/03/2020","predictedDate":"19/03/2021"}},{"name":"UEC","price":"฿2.64","lossChance":"53.4%","linePercentage":"+258.92%","score":2.76,"factorPercentage":"40.00%","advice":"","pe":26.05,"pbv":1.1,"dvdYield":"3.41%","industry":"Industrial","sector":"-","dividend":{"lastDate":"11/03/2021","predictedDate":"11/03/2022"}},{"name":"BSM","price":"฿0.39","lossChance":"53.4%","linePercentage":"+100.00%","score":2.7,"factorPercentage":"28.20%","advice":"","pe":"","pbv":1.5,"dvdYield":"N.A.%","industry":"Property & Construction","sector":"-","dividend":{"lastDate":"07/05/2019","predictedDate":"07/05/2020"}},{"name":"NINE","price":"฿3.90","lossChance":"53.4%","linePercentage":"+1,000%","score":2.67,"factorPercentage":"39.20%","advice":"","pe":39.74,"pbv":4.43,"dvdYield":"N.A.%","industry":"Services","sector":"-","dividend":{"lastDate":"-","predictedDate":"-"}},{"name":"CHEWA","price":"฿0.96","lossChance":"53.4%","linePercentage":"+100.00%","score":2.66,"factorPercentage":"42.60%","advice":"","pe":6.94,"pbv":0.65,"dvdYield":"2.18%","industry":"Property & Construction","sector":"-","dividend":{"lastDate":"08/04/2021","predictedDate":"08/04/2022"}},{"name":"GTB","price":"฿1.07","lossChance":"53.4%","linePercentage":"+244.10%","score":2.63,"factorPercentage":"34.60%","advice":"","pe":62.39,"pbv":1.42,"dvdYield":"1.87%","industry":"Industrial","sector":"-","dividend":{"lastDate":"29/04/2021","predictedDate":"29/04/2022"}},{"name":"QLT","price":"฿4.38","lossChance":"53.4%","linePercentage":"+44.53%","score":2.57,"factorPercentage":"31.60%","advice":"","pe":19.64,"pbv":0.97,"dvdYield":"6.85%","industry":"Services","sector":"-","dividend":{"lastDate":"08/03/2021","predictedDate":"08/03/2022"}},{"name":"IRCP","price":"฿0.98","lossChance":"53.4%","linePercentage":"+531.47%","score":2.55,"factorPercentage":"35.20%","advice":"","pe":"","pbv":3.03,"dvdYield":"N.A.%","industry":"Technology","sector":"-","dividend":{"lastDate":"-","predictedDate":"-"}},{"name":"THMUI","price":"฿1.11","lossChance":"53.4%","linePercentage":"+1,000%","score":2.55,"factorPercentage":"25.80%","advice":"","pe":"","pbv":1.03,"dvdYield":"N.A.%","industry":"Services","sector":"-","dividend":{"lastDate":"25/07/2019","predictedDate":"25/07/2020"}},{"name":"LIT","price":"฿3.90","lossChance":"49.5%","linePercentage":"+31.31%","score":2.54,"factorPercentage":"26.80%","advice":"","pe":16.08,"pbv":0.83,"dvdYield":"4.62%","industry":"Financials","sector":"-","dividend":{"lastDate":"09/03/2021","predictedDate":"09/03/2022"}},{"name":"SEAOIL","price":"฿2.74","lossChance":"53.4%","linePercentage":"+100.00%","score":2.53,"factorPercentage":"26.80%","advice":"","pe":81.97,"pbv":1.25,"dvdYield":"0.25%","industry":"Resources","sector":"-","dividend":{"lastDate":"08/03/2021","predictedDate":"08/03/2022"}},{"name":"KCM","price":"฿1.03","lossChance":"53.4%","linePercentage":"+1,000%","score":2.45,"factorPercentage":"28.60%","advice":"","pe":"","pbv":1.55,"dvdYield":"0.44%","industry":"Industrial","sector":"-","dividend":{"lastDate":"12/05/2021","predictedDate":"12/05/2022"}},{"name":"BGT","price":"฿1.07","lossChance":"53.4%","linePercentage":"+89.72%","score":2.39,"factorPercentage":"30.60%","advice":"","pe":"","pbv":0.94,"dvdYield":"N.A.%","industry":"Consumer Products","sector":"-","dividend":{"lastDate":"07/05/2018","predictedDate":"07/05/2019"}},{"name":"RWI","price":"฿2.10","lossChance":"53.4%","linePercentage":"+754.06%","score":2.39,"factorPercentage":"41.00%","advice":"","pe":6.15,"pbv":1.48,"dvdYield":"N.A.%","industry":"Industrial","sector":"-","dividend":{"lastDate":"07/03/2018","predictedDate":"07/03/2019"}},{"name":"TIGER","price":"฿2.76","lossChance":"53.4%","linePercentage":"+82.40%","score":2.36,"factorPercentage":"32.60%","advice":"","pe":28.64,"pbv":2.03,"dvdYield":"3.26%","industry":"Property & Construction","sector":"-","dividend":{"lastDate":"12/03/2021","predictedDate":"12/03/2022"}},{"name":"JAK","price":"฿1.69","lossChance":"53.4%","linePercentage":"+433.55%","score":2.36,"factorPercentage":"32.60%","advice":"","pe":46.61,"pbv":1.27,"dvdYield":"2.37%","industry":"Property & Construction","sector":"-","dividend":{"lastDate":"17/03/2021","predictedDate":"17/03/2022"}},{"name":"HPT","price":"฿0.79","lossChance":"53.4%","linePercentage":"+1,000%","score":2.35,"factorPercentage":"25.20%","advice":"","pe":"","pbv":2.19,"dvdYield":"N.A.%","industry":"Consumer Products","sector":"-","dividend":{"lastDate":"26/11/2019","predictedDate":"26/11/2020"}},{"name":"K","price":"฿1.37","lossChance":"53.4%","linePercentage":"+100.00%","score":2.34,"factorPercentage":"34.60%","advice":"","pe":"","pbv":2.12,"dvdYield":"N.A.%","industry":"Property & Construction","sector":"-","dividend":{"lastDate":"07/05/2019","predictedDate":"07/05/2020"}},{"name":"KASET","price":"฿1.76","lossChance":"53.4%","linePercentage":"+100.00%","score":2.32,"factorPercentage":"24.80%","advice":"","pe":"","pbv":1.76,"dvdYield":"N.A.%","industry":"Agro & Food Industry","sector":"-","dividend":{"lastDate":"11/03/2019","predictedDate":"11/03/2020"}},{"name":"COMAN","price":"฿5.10","lossChance":"53.4%","linePercentage":"+100.00%","score":2.31,"factorPercentage":"22.40%","advice":"","pe":"","pbv":1.65,"dvdYield":"N.A.%","industry":"Technology","sector":"-","dividend":{"lastDate":"10/04/2020","predictedDate":"10/04/2021"}},{"name":"OTO","price":"฿7.30","lossChance":"53.4%","linePercentage":"+1,000%","score":2.28,"factorPercentage":"34.40%","advice":"","pe":"","pbv":3.55,"dvdYield":"11.23%","industry":"Services","sector":"-","dividend":{"lastDate":"04/12/2020","predictedDate":"04/12/2021"}},{"name":"HEMP","price":"฿0.54","lossChance":"53.4%","linePercentage":"+100.00%","score":2.21,"factorPercentage":"23.00%","advice":"","pe":"","pbv":9.93,"dvdYield":"N.A.%","industry":"Services","sector":"-","dividend":{"lastDate":"-","predictedDate":"-"}},{"name":"PSTC","price":"฿2.38","lossChance":"53.4%","linePercentage":"+100.00%","score":2.18,"factorPercentage":"30.00%","advice":"","pe":"","pbv":0.97,"dvdYield":"N.A.%","industry":"Resources","sector":"-","dividend":{"lastDate":"13/03/2020","predictedDate":"13/03/2021"}},{"name":"SIMAT","price":"฿5.65","lossChance":"53.4%","linePercentage":"+100.00%","score":2.11,"factorPercentage":"31.00%","advice":"","pe":113.24,"pbv":6.4,"dvdYield":"N.A.%","industry":"Technology","sector":"-","dividend":{"lastDate":"-","predictedDate":"-"}},{"name":"DV8","price":"฿0.54","lossChance":"53.4%","linePercentage":"+880.79%","score":2.11,"factorPercentage":"41.40%","advice":"","pe":"","pbv":1.61,"dvdYield":"N.A.%","industry":"Services","sector":"-","dividend":{"lastDate":"-","predictedDate":"-"}},{"name":"CMO","price":"฿1.21","lossChance":"53.4%","linePercentage":"+100.00%","score":2.08,"factorPercentage":"26.60%","advice":"","pe":"","pbv":0.67,"dvdYield":"N.A.%","industry":"Services","sector":"-","dividend":{"lastDate":"22/04/2020","predictedDate":"22/04/2021"}},{"name":"CIG","price":"฿0.69","lossChance":"53.4%","linePercentage":"+100.00%","score":2.07,"factorPercentage":"32.60%","advice":"","pe":"","pbv":1.82,"dvdYield":"N.A.%","industry":"Industrial","sector":"-","dividend":{"lastDate":"-","predictedDate":"-"}},{"name":"NEWS","price":"฿0.01","lossChance":"53.4%","linePercentage":"+100.00%","score":2.05,"factorPercentage":"32.40%","advice":"","pe":5.54,"pbv":0.98,"dvdYield":"N.A.%","industry":"Services","sector":"-","dividend":{"lastDate":"-","predictedDate":"-"}},{"name":"THANA","price":"฿1.39","lossChance":"53.4%","linePercentage":"+100.00%","score":2.01,"factorPercentage":"30.60%","advice":"","pe":"","pbv":0.96,"dvdYield":"N.A.%","industry":"Property & Construction","sector":"-","dividend":{"lastDate":"-","predictedDate":"-"}},{"name":"IMH","price":"฿8.05","lossChance":"57.0%","linePercentage":"+1,000%","score":1.95,"factorPercentage":"23.40%","advice":"","pe":"","pbv":4.12,"dvdYield":"N.A.%","industry":"Services","sector":"-","dividend":{"lastDate":"-","predictedDate":"-"}},{"name":"JCKH","price":"฿0.43","lossChance":"51.3%","linePercentage":"+21.24%","score":1.92,"factorPercentage":"22.80%","advice":"","pe":"","pbv":39.54,"dvdYield":"N.A.%","industry":"Agro & Food Industry","sector":"-","dividend":{"lastDate":"-","predictedDate":"-"}},{"name":"SLM","price":"฿0.95","lossChance":"54.6%","linePercentage":"+100.00%","score":1.91,"factorPercentage":"45.40%","advice":"","pe":"","pbv":"","dvdYield":"-%","industry":"Services","sector":"-","dividend":{"lastDate":"-","predictedDate":"-"}},{"name":"SGF","price":"฿1.10","lossChance":"57.0%","linePercentage":"+263.00%","score":1.87,"factorPercentage":"31.40%","advice":"","pe":26.95,"pbv":0.85,"dvdYield":"N.A.%","industry":"Financials","sector":"-","dividend":{"lastDate":"-","predictedDate":"-"}},{"name":"MORE","price":"฿1.27","lossChance":"57.0%","linePercentage":"+100.00%","score":1.85,"factorPercentage":"30.20%","advice":"","pe":"","pbv":29.08,"dvdYield":"N.A.%","industry":"Services","sector":"-","dividend":{"lastDate":"-","predictedDate":"-"}},{"name":"GCAP","price":"฿2.26","lossChance":"57.0%","linePercentage":"+100.00%","score":1.82,"factorPercentage":"21.60%","advice":"","pe":"","pbv":1.41,"dvdYield":"2.21%","industry":"Financials","sector":"-","dividend":{"lastDate":"12/03/2021","predictedDate":"12/03/2022"}},{"name":"META","price":"฿0.56","lossChance":"57.0%","linePercentage":"+100.00%","score":1.79,"factorPercentage":"27.20%","advice":"","pe":"","pbv":0.42,"dvdYield":"N.A.%","industry":"Property & Construction","sector":"-","dividend":{"lastDate":"-","predictedDate":"-"}},{"name":"GSC","price":"฿1.53","lossChance":"57.0%","linePercentage":"+100.00%","score":1.77,"factorPercentage":"22.40%","advice":"","pe":"","pbv":1.76,"dvdYield":"N.A.%","industry":"Services","sector":"-","dividend":{"lastDate":"22/08/2019","predictedDate":"22/08/2020"}},{"name":"PPS","price":"฿0.61","lossChance":"57.0%","linePercentage":"+100.00%","score":1.76,"factorPercentage":"24.40%","advice":"","pe":"","pbv":1.88,"dvdYield":"N.A.%","industry":"Property & Construction","sector":"-","dividend":{"lastDate":"03/05/2019","predictedDate":"03/05/2020"}},{"name":"TMC","price":"฿1.02","lossChance":"57.0%","linePercentage":"+100.00%","score":1.68,"factorPercentage":"27.40%","advice":"","pe":"","pbv":1.33,"dvdYield":"N.A.%","industry":"Industrial","sector":"-","dividend":{"lastDate":"-","predictedDate":"-"}},{"name":"BTW","price":"฿1.21","lossChance":"57.0%","linePercentage":"+75.67%","score":1.59,"factorPercentage":"37.20%","advice":"","pe":56.2,"pbv":0.8,"dvdYield":"1.65%","industry":"Property & Construction","sector":"-","dividend":{"lastDate":"09/03/2021","predictedDate":"09/03/2022"}},{"name":"MVP","price":"฿5.75","lossChance":"57.0%","linePercentage":"+100.00%","score":1.58,"factorPercentage":"25.20%","advice":"","pe":"","pbv":8.92,"dvdYield":"N.A.%","industry":"Services","sector":"-","dividend":{"lastDate":"-","predictedDate":"-"}},{"name":"UPA","price":"฿0.47","lossChance":"57.0%","linePercentage":"+100.00%","score":1.51,"factorPercentage":"39.00%","advice":"","pe":"","pbv":1.6,"dvdYield":"N.A.%","industry":"Resources","sector":"-","dividend":{"lastDate":"-","predictedDate":"-"}},{"name":"UREKA","price":"฿0.89","lossChance":"57.0%","linePercentage":"+100.00%","score":1.49,"factorPercentage":"25.00%","advice":"","pe":"","pbv":2.67,"dvdYield":"N.A.%","industry":"Industrial","sector":"-","dividend":{"lastDate":"-","predictedDate":"-"}},{"name":"CRD","price":"฿0.73","lossChance":"57.0%","linePercentage":"+100.00%","score":1.31,"factorPercentage":"28.00%","advice":"","pe":"","pbv":1.04,"dvdYield":"N.A.%","industry":"Property & Construction","sector":"-","dividend":{"lastDate":"22/04/2020","predictedDate":"22/04/2021"}},{"name":"CHOW","price":"฿3.82","lossChance":"49.6%","linePercentage":"+2.28%","score":1.1,"factorPercentage":"27.60%","advice":"","pe":"","pbv":4.17,"dvdYield":"N.A.%","industry":"Industrial","sector":"-","dividend":{"lastDate":"-","predictedDate":"-"}},{"name":"CHO","price":"฿0.88","lossChance":"57.0%","linePercentage":"+100.00%","score":1.08,"factorPercentage":"18.80%","advice":"","pe":"","pbv":1.35,"dvdYield":"N.A.%","industry":"Industrial","sector":"-","dividend":{"lastDate":"-","predictedDate":"-"}},{"name":"JSP","price":"฿0.36","lossChance":"57.0%","linePercentage":"+100.00%","score":1.06,"factorPercentage":"18.00%","advice":"","pe":"","pbv":0.36,"dvdYield":"N.A.%","industry":"Property & Construction","sector":"-","dividend":{"lastDate":"07/05/2019","predictedDate":"07/05/2020"}},{"name":"RP","price":"฿2.28","lossChance":"57.0%","linePercentage":"+788.85%","score":1.04,"factorPercentage":"18.40%","advice":"","pe":"","pbv":0.59,"dvdYield":"N.A.%","industry":"Services","sector":"-","dividend":{"lastDate":"10/08/2020","predictedDate":"10/08/2021"}},{"name":"BC","price":"฿2.28","lossChance":"57.2%","linePercentage":"+100.00%","score":0.9,"factorPercentage":"19.40%","advice":"","pe":"","pbv":1.54,"dvdYield":"N.A.%","industry":"Property & Construction","sector":"-","dividend":{"lastDate":"27/12/2019","predictedDate":"27/12/2020"}},{"name":"STOWER","price":"฿0.07","lossChance":"57.2%","linePercentage":"+100.00%","score":0.88,"factorPercentage":"26.20%","advice":"","pe":"","pbv":12.57,"dvdYield":"N.A.%","industry":"Resources","sector":"-","dividend":{"lastDate":"-","predictedDate":"-"}},{"name":"PROUD","price":"฿1.00","lossChance":"57.2%","linePercentage":"+100.00%","score":0.83,"factorPercentage":"32.20%","advice":"","pe":"","pbv":0.95,"dvdYield":"N.A.%","industry":"Property & Construction","sector":"-","dividend":{"lastDate":"-","predictedDate":"-"}},{"name":"T","price":"฿0.06","lossChance":"57.2%","linePercentage":"+100.00%","score":0.83,"factorPercentage":"24.00%","advice":"","pe":"","pbv":4.27,"dvdYield":"N.A.%","industry":"Property & Construction","sector":"-","dividend":{"lastDate":"-","predictedDate":"-"}},{"name":"ARIN","price":"฿1.18","lossChance":"57.2%","linePercentage":"+100.00%","score":0.82,"factorPercentage":"19.00%","advice":"","pe":"","pbv":1.64,"dvdYield":"N.A.%","industry":"Property & Construction","sector":"-","dividend":{"lastDate":"-","predictedDate":"-"}},{"name":"DIMET","price":"฿0.63","lossChance":"57.2%","linePercentage":"+100.00%","score":0.65,"factorPercentage":"18.00%","advice":"","pe":"","pbv":6.35,"dvdYield":"N.A.%","industry":"Property & Construction","sector":"-","dividend":{"lastDate":"-","predictedDate":"-"}},{"name":"SR","price":"฿1.52","lossChance":"57.2%","linePercentage":"+100.00%","score":0.63,"factorPercentage":"17.00%","advice":"","pe":"","pbv":1.05,"dvdYield":"N.A.%","industry":"Resources","sector":"-","dividend":{"lastDate":"09/03/2020","predictedDate":"09/03/2021"}},{"name":"ACAP","price":"฿1.55","lossChance":"57.2%","linePercentage":"+100.00%","score":0.47,"factorPercentage":"18.80%","advice":"","pe":"","pbv":1.78,"dvdYield":"N.A.%","industry":"Financials","sector":"-","dividend":{"lastDate":"03/05/2018","predictedDate":"03/05/2019"}},{"name":"TSF","price":"฿0.01","lossChance":"61.0%","linePercentage":"+100.00%","score":0.39,"factorPercentage":"18.40%","advice":"","pe":"","pbv":"","dvdYield":"-%","industry":"Services","sector":"-","dividend":{"lastDate":"-","predictedDate":"-"}},{"name":"HYDRO","price":"฿0.37","lossChance":"57.2%","linePercentage":"+100.00%","score":0.37,"factorPercentage":"36.80%","advice":"","pe":"","pbv":63.26,"dvdYield":"N.A.%","industry":"Property & Construction","sector":"-","dividend":{"lastDate":"-","predictedDate":"-"}},{"name":"UMS","price":"฿1.18","lossChance":"57.2%","linePercentage":"+100.00%","score":0.06,"factorPercentage":"24.00%","advice":"","pe":"","pbv":6.39,"dvdYield":"N.A.%","industry":"Resources","sector":"-","dividend":{"lastDate":"-","predictedDate":"-"}},{"name":"STAR","price":"฿3.50","lossChance":"57.2%","linePercentage":"+100.00%","score":0.01,"factorPercentage":"11.40%","advice":"","pe":"","pbv":26.93,"dvdYield":"N.A.%","industry":"Property & Construction","sector":"-","dividend":{"lastDate":"-","predictedDate":"-"}}]}