{"createdAt":"05/01/2022 10:16:16","results":[{"name":"COM7","price":"฿83.75","lossChance":"39.7%","linePercentage":"+26.40%","score":7.69,"factorPercentage":"86.80%","advice":"Strong Buy","pe":44.1,"pbv":22.97,"dvdYield":"1.19%","industry":"Services","sector":"Commerce","dividend":{"lastDate":"29/04/2021","predictedDate":"29/04/2022"}},{"name":"TQM","price":"฿95.25","lossChance":"39.2%","linePercentage":"+51.98%","score":7.24,"factorPercentage":"76.40%","advice":"Sell","pe":33.37,"pbv":12.33,"dvdYield":"2.26%","industry":"Financials","sector":"Insurance","dividend":{"lastDate":"26/08/2021","predictedDate":"26/08/2022"}},{"name":"BCH","price":"฿19.50","lossChance":"40.9%","linePercentage":"-9.50%","score":7.1,"factorPercentage":"79.60%","advice":"Strong Sell","pe":10.47,"pbv":4.61,"dvdYield":"1.18%","industry":"Services","sector":"Health Care Services","dividend":{"lastDate":"31/08/2021","predictedDate":"31/08/2022"}},{"name":"MEGA","price":"฿48.75","lossChance":"39.2%","linePercentage":"+199.40%","score":7.02,"factorPercentage":"79.00%","advice":"Sell","pe":22.64,"pbv":5.69,"dvdYield":"1.85%","industry":"Services","sector":"Commerce","dividend":{"lastDate":"27/08/2021","predictedDate":"27/08/2022"}},{"name":"CHG","price":"฿3.58","lossChance":"41.2%","linePercentage":"-0.48%","score":6.87,"factorPercentage":"79.80%","advice":"Strong Sell","pe":14.89,"pbv":6.84,"dvdYield":"1.40%","industry":"Services","sector":"Health Care Services","dividend":{"lastDate":"24/08/2021","predictedDate":"24/08/2022"}},{"name":"SAWAD","price":"฿62.25","lossChance":"40.4%","linePercentage":"-39.76%","score":6.59,"factorPercentage":"75.20%","advice":"Buy","pe":17.56,"pbv":3.63,"dvdYield":"2.89%","industry":"Financials","sector":"Finance & Securities","dividend":{"lastDate":"05/05/2021","predictedDate":"05/05/2022"}},{"name":"MTC","price":"฿59.00","lossChance":"41.2%","linePercentage":"-4.22%","score":6.48,"factorPercentage":"64.20%","advice":"Buy","pe":23.99,"pbv":5.27,"dvdYield":"0.63%","industry":"Financials","sector":"Finance & Securities","dividend":{"lastDate":"29/04/2021","predictedDate":"29/04/2022"}},{"name":"AEONTS","price":"฿189.00","lossChance":"41.5%","linePercentage":"-21.14%","score":6.25,"factorPercentage":"62.20%","advice":"Buy","pe":11.75,"pbv":2.61,"dvdYield":"2.38%","industry":"Financials","sector":"Finance & Securities","dividend":{"lastDate":"18/10/2021","predictedDate":"18/10/2022"}},{"name":"SYNEX","price":"฿34.50","lossChance":"42.7%","linePercentage":"+614.59%","score":6.21,"factorPercentage":"68.80%","advice":"Buy","pe":38.26,"pbv":8.1,"dvdYield":"1.57%","industry":"Technology","sector":"Information & Communication Technology","dividend":{"lastDate":"24/08/2021","predictedDate":"24/08/2022"}},{"name":"EPG","price":"฿11.90","lossChance":"42.7%","linePercentage":"+197.73%","score":6.19,"factorPercentage":"66.20%","advice":"Strong Buy","pe":19.65,"pbv":2.9,"dvdYield":"2.35%","industry":"Property & Construction","sector":"Construction Materials","dividend":{"lastDate":"25/11/2021","predictedDate":"25/11/2022"}},{"name":"CBG","price":"฿119.00","lossChance":"42.7%","linePercentage":"+73.28%","score":6.14,"factorPercentage":"63.60%","advice":"Neutral","pe":37.88,"pbv":12.39,"dvdYield":"2.02%","industry":"Agro & Food Industry","sector":"Food & Beverage","dividend":{"lastDate":"27/08/2021","predictedDate":"27/08/2022"}},{"name":"KTC","price":"฿60.00","lossChance":"42.7%","linePercentage":"+48.35%","score":6.09,"factorPercentage":"66.20%","advice":"Buy","pe":25.99,"pbv":6.06,"dvdYield":"1.47%","industry":"Financials","sector":"Finance & Securities","dividend":{"lastDate":"19/04/2021","predictedDate":"19/04/2022"}},{"name":"GLOBAL","price":"฿20.10","lossChance":"46.4%","linePercentage":"+82.58%","score":5.94,"factorPercentage":"66.20%","advice":"Sell","pe":31.09,"pbv":4.92,"dvdYield":"0.88%","industry":"Services","sector":"Commerce","dividend":{"lastDate":"24/02/2021","predictedDate":"24/02/2022"}},{"name":"TISCO","price":"฿98.50","lossChance":"43.2%","linePercentage":"+9.63%","score":5.85,"factorPercentage":"66.60%","advice":"Strong Buy","pe":11.9,"pbv":2,"dvdYield":"6.40%","industry":"Financials","sector":"Banking","dividend":{"lastDate":"28/04/2021","predictedDate":"28/04/2022"}},{"name":"EA","price":"฿97.25","lossChance":"46.4%","linePercentage":"+58.33%","score":5.85,"factorPercentage":"58.80%","advice":"Buy","pe":63.61,"pbv":11.8,"dvdYield":"0.31%","industry":"Resources","sector":"Energy & Utilities","dividend":{"lastDate":"12/03/2021","predictedDate":"12/03/2022"}},{"name":"HMPRO","price":"฿14.80","lossChance":"46.4%","linePercentage":"+123.33%","score":5.81,"factorPercentage":"56.60%","advice":"Strong Buy","pe":37.36,"pbv":9.25,"dvdYield":"2.03%","industry":"Services","sector":"Commerce","dividend":{"lastDate":"15/09/2021","predictedDate":"15/09/2022"}},{"name":"TIDLOR","price":"฿37.75","lossChance":"43.2%","linePercentage":"+3.39%","score":5.76,"factorPercentage":"61.20%","advice":"Strong Buy","pe":29.21,"pbv":4.05,"dvdYield":"N.A.%","industry":"Financials","sector":"Finance & Securities","dividend":{"lastDate":"-","predictedDate":"-"}},{"name":"SCGP","price":"฿68.75","lossChance":"46.4%","linePercentage":"+280.18%","score":5.7,"factorPercentage":"61.20%","advice":"Buy","pe":38.51,"pbv":3.1,"dvdYield":"0.65%","industry":"Industrials","sector":"Packaging","dividend":{"lastDate":"09/08/2021","predictedDate":"09/08/2022"}},{"name":"SPALI","price":"฿22.70","lossChance":"46.4%","linePercentage":"+44.34%","score":5.68,"factorPercentage":"69.80%","advice":"Buy","pe":7.3,"pbv":1.13,"dvdYield":"4.41%","industry":"Property & Construction","sector":"Property Development","dividend":{"lastDate":"24/08/2021","predictedDate":"24/08/2022"}},{"name":"THANI","price":"฿4.46","lossChance":"41.8%","linePercentage":"-29.01%","score":5.66,"factorPercentage":"50.60%","advice":"Buy","pe":14.55,"pbv":2.27,"dvdYield":"3.81%","industry":"Financials","sector":"Finance & Securities","dividend":{"lastDate":"04/03/2021","predictedDate":"04/03/2022"}},{"name":"PTG","price":"฿15.20","lossChance":"41.8%","linePercentage":"-73.71%","score":5.58,"factorPercentage":"59.80%","advice":"Buy","pe":14.39,"pbv":3.1,"dvdYield":"3.29%","industry":"Resources","sector":"Energy & Utilities","dividend":{"lastDate":"11/03/2021","predictedDate":"11/03/2022"}},{"name":"SCC","price":"฿387.00","lossChance":"43.6%","linePercentage":"+18.47%","score":5.58,"factorPercentage":"63.80%","advice":"Neutral","pe":9.9,"pbv":1.29,"dvdYield":"3.62%","industry":"Property & Construction","sector":"Construction Materials","dividend":{"lastDate":"13/08/2021","predictedDate":"13/08/2022"}},{"name":"TVO","price":"฿31.00","lossChance":"46.4%","linePercentage":"+79.25%","score":5.51,"factorPercentage":"77.20%","advice":"Buy","pe":10.3,"pbv":2.66,"dvdYield":"5.48%","industry":"Agro & Food Industry","sector":"Food & Beverage","dividend":{"lastDate":"27/08/2021","predictedDate":"27/08/2022"}},{"name":"TU","price":"฿19.80","lossChance":"43.3%","linePercentage":"-8.72%","score":5.5,"factorPercentage":"59.80%","advice":"Buy","pe":12.22,"pbv":1.62,"dvdYield":"3.64%","industry":"Agro & Food Industry","sector":"Food & Beverage","dividend":{"lastDate":"23/08/2021","predictedDate":"23/08/2022"}},{"name":"STGT","price":"฿29.50","lossChance":"41.8%","linePercentage":"-46.60%","score":5.39,"factorPercentage":"69.60%","advice":"Sell","pe":2.78,"pbv":2.12,"dvdYield":"8.88%","industry":"Consumer Products","sector":"Personal Products & Pharmaceuticals","dividend":{"lastDate":"19/11/2021","predictedDate":"19/11/2022"}},{"name":"ORI","price":"฿11.60","lossChance":"46.4%","linePercentage":"+65.08%","score":5.38,"factorPercentage":"61.80%","advice":"Strong Buy","pe":9.39,"pbv":2.27,"dvdYield":"4.22%","industry":"Property & Construction","sector":"Property Development","dividend":{"lastDate":"24/08/2021","predictedDate":"24/08/2022"}},{"name":"RS","price":"฿21.70","lossChance":"46.4%","linePercentage":"+503.86%","score":5.37,"factorPercentage":"54.80%","advice":"Buy","pe":70.18,"pbv":9.46,"dvdYield":"N.A.%","industry":"Services","sector":"Commerce","dividend":{"lastDate":"04/03/2020","predictedDate":"04/03/2021"}},{"name":"TCAP","price":"฿38.50","lossChance":"46.4%","linePercentage":"+84.07%","score":5.35,"factorPercentage":"46.40%","advice":"Strong Buy","pe":9.6,"pbv":0.64,"dvdYield":"7.79%","industry":"Financials","sector":"Banking","dividend":{"lastDate":"13/09/2021","predictedDate":"13/09/2022"}},{"name":"KBANK","price":"฿145.50","lossChance":"46.4%","linePercentage":"+46.33%","score":5.23,"factorPercentage":"59.00%","advice":"Strong Buy","pe":8.32,"pbv":0.74,"dvdYield":"1.72%","industry":"Financials","sector":"Banking","dividend":{"lastDate":"08/09/2021","predictedDate":"08/09/2022"}},{"name":"PTTEP","price":"฿119.50","lossChance":"43.2%","linePercentage":"+0.94%","score":5.2,"factorPercentage":"51.00%","advice":"Strong Buy","pe":15.43,"pbv":1.16,"dvdYield":"3.56%","industry":"Resources","sector":"Energy & Utilities","dividend":{"lastDate":"11/08/2021","predictedDate":"11/08/2022"}},{"name":"ADVANC","price":"฿228.00","lossChance":"43.2%","linePercentage":"+5.48%","score":5.14,"factorPercentage":"54.20%","advice":"Buy","pe":24.91,"pbv":9.07,"dvdYield":"3.03%","industry":"Technology","sector":"Information & Communication Technology","dividend":{"lastDate":"16/08/2021","predictedDate":"16/08/2022"}},{"name":"GPSC","price":"฿88.25","lossChance":"41.8%","linePercentage":"-31.24%","score":5.12,"factorPercentage":"40.00%","advice":"Buy","pe":32.71,"pbv":2.36,"dvdYield":"1.70%","industry":"Resources","sector":"Energy & Utilities","dividend":{"lastDate":"08/09/2021","predictedDate":"08/09/2022"}},{"name":"JMT","price":"฿69.50","lossChance":"46.4%","linePercentage":"+130.70%","score":5.05,"factorPercentage":"63.80%","advice":"Strong Buy","pe":75.81,"pbv":11.22,"dvdYield":"0.89%","industry":"Financials","sector":"Finance & Securities","dividend":{"lastDate":"23/08/2021","predictedDate":"23/08/2022"}},{"name":"ACE","price":"฿3.52","lossChance":"43.2%","linePercentage":"-16.31%","score":5.04,"factorPercentage":"53.80%","advice":"Sell","pe":25.73,"pbv":2.77,"dvdYield":"1.36%","industry":"Resources","sector":"Energy & Utilities","dividend":{"lastDate":"11/03/2021","predictedDate":"11/03/2022"}},{"name":"BDMS","price":"฿22.40","lossChance":"46.4%","linePercentage":"+373.15%","score":5.02,"factorPercentage":"48.60%","advice":"Strong Sell","pe":46.3,"pbv":4.41,"dvdYield":"2.46%","industry":"Services","sector":"Health Care Services","dividend":{"lastDate":"12/10/2021","predictedDate":"12/10/2022"}},{"name":"KCE","price":"฿88.50","lossChance":"46.4%","linePercentage":"+569.86%","score":5.01,"factorPercentage":"65.60%","advice":"Sell","pe":49.66,"pbv":8.25,"dvdYield":"0.90%","industry":"Technology","sector":"Electronic Components","dividend":{"lastDate":"23/08/2021","predictedDate":"23/08/2022"}},{"name":"OSP","price":"฿34.50","lossChance":"48.9%","linePercentage":"+219.02%","score":4.94,"factorPercentage":"52.00%","advice":"Buy","pe":31.84,"pbv":5.43,"dvdYield":"3.19%","industry":"Agro & Food Industry","sector":"Food & Beverage","dividend":{"lastDate":"24/08/2021","predictedDate":"24/08/2022"}},{"name":"SCB","price":"฿128.00","lossChance":"48.9%","linePercentage":"+128.22%","score":4.9,"factorPercentage":"54.20%","advice":"Buy","pe":13.31,"pbv":1.02,"dvdYield":"1.80%","industry":"Financials","sector":"Banking","dividend":{"lastDate":"06/09/2021","predictedDate":"06/09/2022"}},{"name":"AP","price":"฿9.55","lossChance":"44.5%","linePercentage":"+27.47%","score":4.85,"factorPercentage":"58.00%","advice":"Buy","pe":6.69,"pbv":0.96,"dvdYield":"4.71%","industry":"Property & Construction","sector":"Property Development","dividend":{"lastDate":"11/05/2021","predictedDate":"11/05/2022"}},{"name":"HANA","price":"฿87.50","lossChance":"48.9%","linePercentage":"+293.60%","score":4.84,"factorPercentage":"59.00%","advice":"Sell","pe":30.57,"pbv":2.95,"dvdYield":"1.60%","industry":"Technology","sector":"Electronic Components","dividend":{"lastDate":"29/10/2021","predictedDate":"29/10/2022"}},{"name":"IVL","price":"฿43.50","lossChance":"48.9%","linePercentage":"+47.54%","score":4.75,"factorPercentage":"58.40%","advice":"Buy","pe":11,"pbv":1.57,"dvdYield":"1.61%","industry":"Industrials","sector":"Petrochemicals & Chemicals","dividend":{"lastDate":"25/11/2021","predictedDate":"25/11/2022"}},{"name":"KTB","price":"฿13.50","lossChance":"48.9%","linePercentage":"+55.07%","score":4.75,"factorPercentage":"48.00%","advice":"Strong Buy","pe":9.39,"pbv":0.53,"dvdYield":"2.04%","industry":"Financials","sector":"Banking","dividend":{"lastDate":"21/04/2021","predictedDate":"21/04/2022"}},{"name":"KEX","price":"฿30.00","lossChance":"44.5%","linePercentage":"-4.27%","score":4.74,"factorPercentage":"46.80%","advice":"Strong Sell","pe":50.87,"pbv":5.32,"dvdYield":"0.73%","industry":"Services","sector":"Transportation & Logistics","dividend":{"lastDate":"24/08/2021","predictedDate":"24/08/2022"}},{"name":"TTB","price":"฿1.47","lossChance":"44.9%","linePercentage":"+19.09%","score":4.72,"factorPercentage":"42.40%","advice":"Buy","pe":15.94,"pbv":0.68,"dvdYield":"3.05%","industry":"Financials","sector":"Banking","dividend":{"lastDate":"29/04/2021","predictedDate":"29/04/2022"}},{"name":"STA","price":"฿30.00","lossChance":"42.4%","linePercentage":"-59.34%","score":4.65,"factorPercentage":"64.60%","advice":"Sell","pe":2.34,"pbv":0.99,"dvdYield":"7.50%","industry":"Agro & Food Industry","sector":"Agribusiness","dividend":{"lastDate":"19/11/2021","predictedDate":"19/11/2022"}},{"name":"PTT","price":"฿38.00","lossChance":"44.9%","linePercentage":"+23.47%","score":4.61,"factorPercentage":"55.40%","advice":"Buy","pe":11.55,"pbv":1.11,"dvdYield":"2.63%","industry":"Resources","sector":"Energy & Utilities","dividend":{"lastDate":"29/09/2021","predictedDate":"29/09/2022"}},{"name":"RBF","price":"฿22.70","lossChance":"48.9%","linePercentage":"+1,000%","score":4.58,"factorPercentage":"46.40%","advice":"Strong Buy","pe":103.57,"pbv":10.98,"dvdYield":"0.66%","industry":"Agro & Food Industry","sector":"Food & Beverage","dividend":{"lastDate":"29/04/2021","predictedDate":"29/04/2022"}},{"name":"KKP","price":"฿61.50","lossChance":"48.9%","linePercentage":"+106.74%","score":4.55,"factorPercentage":"49.00%","advice":"Strong Buy","pe":9.64,"pbv":1.06,"dvdYield":"3.66%","industry":"Financials","sector":"Banking","dividend":{"lastDate":"08/09/2021","predictedDate":"08/09/2022"}},{"name":"GULF","price":"฿47.50","lossChance":"48.9%","linePercentage":"+130.35%","score":4.55,"factorPercentage":"51.20%","advice":"Strong Buy","pe":86.13,"pbv":6.25,"dvdYield":"0.80%","industry":"Resources","sector":"Energy & Utilities","dividend":{"lastDate":"05/03/2021","predictedDate":"05/03/2022"}},{"name":"BH","price":"฿141.00","lossChance":"48.9%","linePercentage":"+1,000%","score":4.55,"factorPercentage":"46.80%","advice":"Neutral","pe":144.49,"pbv":6.75,"dvdYield":"2.27%","industry":"Services","sector":"Health Care Services","dividend":{"lastDate":"26/08/2021","predictedDate":"26/08/2022"}},{"name":"OR","price":"฿27.25","lossChance":"48.9%","linePercentage":"+153.21%","score":4.42,"factorPercentage":"55.20%","advice":"Buy","pe":27.15,"pbv":3.38,"dvdYield":"0.36%","industry":"Resources","sector":"Energy & Utilities","dividend":{"lastDate":"08/09/2021","predictedDate":"08/09/2022"}},{"name":"BLA","price":"฿37.50","lossChance":"48.9%","linePercentage":"+298.88%","score":4.34,"factorPercentage":"49.20%","advice":"Buy","pe":20.75,"pbv":1.35,"dvdYield":"0.61%","industry":"Financials","sector":"Insurance","dividend":{"lastDate":"11/05/2021","predictedDate":"11/05/2022"}},{"name":"AMATA","price":"฿21.10","lossChance":"44.5%","linePercentage":"-3.54%","score":4.2,"factorPercentage":"44.00%","advice":"Buy","pe":22.93,"pbv":1.43,"dvdYield":"1.39%","industry":"Property & Construction","sector":"Property Development","dividend":{"lastDate":"27/08/2021","predictedDate":"27/08/2022"}},{"name":"CPALL","price":"฿59.75","lossChance":"48.9%","linePercentage":"+82.31%","score":4.13,"factorPercentage":"40.60%","advice":"Neutral","pe":54.47,"pbv":5.59,"dvdYield":"1.51%","industry":"Services","sector":"Commerce","dividend":{"lastDate":"05/05/2021","predictedDate":"05/05/2022"}},{"name":"LH","price":"฿8.90","lossChance":"48.9%","linePercentage":"+162.43%","score":4.12,"factorPercentage":"49.60%","advice":"Strong Buy","pe":14.61,"pbv":2.22,"dvdYield":"5.62%","industry":"Property & Construction","sector":"Property Development","dividend":{"lastDate":"24/08/2021","predictedDate":"24/08/2022"}},{"name":"BGRIM","price":"฿40.50","lossChance":"42.4%","linePercentage":"-43.38%","score":4.1,"factorPercentage":"45.40%","advice":"Neutral","pe":39.74,"pbv":3.59,"dvdYield":"1.11%","industry":"Resources","sector":"Energy & Utilities","dividend":{"lastDate":"26/08/2021","predictedDate":"26/08/2022"}},{"name":"CKP","price":"฿5.05","lossChance":"44.9%","linePercentage":"+13.75%","score":4.09,"factorPercentage":"47.80%","advice":"Neutral","pe":19.89,"pbv":1.67,"dvdYield":"0.69%","industry":"Resources","sector":"Energy & Utilities","dividend":{"lastDate":"28/04/2021","predictedDate":"28/04/2022"}},{"name":"GUNKUL","price":"฿5.85","lossChance":"48.9%","linePercentage":"+57.44%","score":4.08,"factorPercentage":"50.60%","advice":"Strong Buy","pe":15.22,"pbv":4.04,"dvdYield":"3.08%","industry":"Resources","sector":"Energy & Utilities","dividend":{"lastDate":"25/08/2021","predictedDate":"25/08/2022"}},{"name":"BBL","price":"฿125.00","lossChance":"48.9%","linePercentage":"+68.15%","score":4.05,"factorPercentage":"42.40%","advice":"Strong Buy","pe":10.56,"pbv":0.49,"dvdYield":"2.00%","industry":"Financials","sector":"Banking","dividend":{"lastDate":"08/09/2021","predictedDate":"08/09/2022"}},{"name":"PLANB","price":"฿8.05","lossChance":"48.9%","linePercentage":"+793.63%","score":4.05,"factorPercentage":"45.20%","advice":"Strong Buy","pe":636.64,"pbv":6.49,"dvdYield":"0.89%","industry":"Services","sector":"Media & Publishing","dividend":{"lastDate":"24/11/2020","predictedDate":"24/11/2021"}},{"name":"RCL","price":"฿50.00","lossChance":"42.4%","linePercentage":"-36.17%","score":4,"factorPercentage":"60.00%","advice":"Strong Buy","pe":3.73,"pbv":2.17,"dvdYield":"1.00%","industry":"Services","sector":"Transportation & Logistics","dividend":{"lastDate":"18/11/2021","predictedDate":"18/11/2022"}},{"name":"STARK","price":"฿4.62","lossChance":"50.3%","linePercentage":"+303.55%","score":3.97,"factorPercentage":"59.20%","advice":"Sell","pe":23.71,"pbv":9.47,"dvdYield":"N.A.%","industry":"Industrials","sector":"Industrial Materials & Machinery","dividend":{"lastDate":"-","predictedDate":"-"}},{"name":"VGI","price":"฿6.60","lossChance":"50.3%","linePercentage":"+659.60%","score":3.94,"factorPercentage":"46.60%","advice":"Sell","pe":52.99,"pbv":3.68,"dvdYield":"0.92%","industry":"Services","sector":"Media & Publishing","dividend":{"lastDate":"15/07/2021","predictedDate":"15/07/2022"}},{"name":"SINGER","price":"฿53.25","lossChance":"50.3%","linePercentage":"+390.99%","score":3.93,"factorPercentage":"48.60%","advice":"Strong Buy","pe":69.62,"pbv":11.1,"dvdYield":"0.27%","industry":"Services","sector":"Commerce","dividend":{"lastDate":"24/08/2021","predictedDate":"24/08/2022"}},{"name":"CPF","price":"฿27.00","lossChance":"46.2%","linePercentage":"+28.62%","score":3.92,"factorPercentage":"36.00%","advice":"Strong Buy","pe":17.85,"pbv":1.08,"dvdYield":"3.72%","industry":"Agro & Food Industry","sector":"Food & Beverage","dividend":{"lastDate":"30/08/2021","predictedDate":"30/08/2022"}},{"name":"INTUCH","price":"฿80.00","lossChance":"50.3%","linePercentage":"+318.71%","score":3.92,"factorPercentage":"52.60%","advice":"Strong Buy","pe":23.75,"pbv":6.74,"dvdYield":"3.12%","industry":"Technology","sector":"Information & Communication Technology","dividend":{"lastDate":"17/08/2021","predictedDate":"17/08/2022"}},{"name":"JMART","price":"฿58.00","lossChance":"50.3%","linePercentage":"+133.97%","score":3.75,"factorPercentage":"41.20%","advice":"Strong Buy","pe":72.44,"pbv":15.25,"dvdYield":"0.82%","industry":"Technology","sector":"Information & Communication Technology","dividend":{"lastDate":"23/08/2021","predictedDate":"23/08/2022"}},{"name":"CPN","price":"฿56.00","lossChance":"50.3%","linePercentage":"+81.95%","score":3.74,"factorPercentage":"36.60%","advice":"Buy","pe":34.06,"pbv":3.51,"dvdYield":"1.25%","industry":"Property & Construction","sector":"Property Development","dividend":{"lastDate":"04/03/2021","predictedDate":"04/03/2022"}},{"name":"STEC","price":"฿15.00","lossChance":"46.2%","linePercentage":"+41.82%","score":3.72,"factorPercentage":"43.80%","advice":"Strong Buy","pe":28.48,"pbv":1.44,"dvdYield":"2.00%","industry":"Property & Construction","sector":"Construction Services","dividend":{"lastDate":"25/03/2021","predictedDate":"25/03/2022"}},{"name":"DOHOME","price":"฿23.20","lossChance":"50.3%","linePercentage":"+116.95%","score":3.72,"factorPercentage":"53.80%","advice":"Sell","pe":33.05,"pbv":5.33,"dvdYield":"0.04%","industry":"Services","sector":"Commerce","dividend":{"lastDate":"03/03/2021","predictedDate":"03/03/2022"}},{"name":"EGCO","price":"฿176.50","lossChance":"43.3%","linePercentage":"-29.08%","score":3.71,"factorPercentage":"31.00%","advice":"Buy","pe":18.68,"pbv":0.82,"dvdYield":"3.68%","industry":"Resources","sector":"Energy & Utilities","dividend":{"lastDate":"27/08/2021","predictedDate":"27/08/2022"}},{"name":"BCPG","price":"฿12.00","lossChance":"44.6%","linePercentage":"-23.31%","score":3.47,"factorPercentage":"35.60%","advice":"Sell","pe":16.67,"pbv":1.36,"dvdYield":"2.21%","industry":"Resources","sector":"Energy & Utilities","dividend":{"lastDate":"07/09/2021","predictedDate":"07/09/2022"}},{"name":"RATCH","price":"฿45.25","lossChance":"46.2%","linePercentage":"+30.72%","score":3.44,"factorPercentage":"46.60%","advice":"Buy","pe":8.44,"pbv":0.96,"dvdYield":"5.30%","industry":"Resources","sector":"Energy & Utilities","dividend":{"lastDate":"07/09/2021","predictedDate":"07/09/2022"}},{"name":"BPP","price":"฿17.20","lossChance":"50.3%","linePercentage":"+139.47%","score":3.43,"factorPercentage":"45.80%","advice":"Sell","pe":13.25,"pbv":1.14,"dvdYield":"3.78%","industry":"Resources","sector":"Energy & Utilities","dividend":{"lastDate":"09/09/2021","predictedDate":"09/09/2022"}},{"name":"SUPER","price":"฿0.95","lossChance":"43.3%","linePercentage":"-61.24%","score":3.38,"factorPercentage":"39.00%","advice":"Buy","pe":12.73,"pbv":1.33,"dvdYield":"0.63%","industry":"Resources","sector":"Energy & Utilities","dividend":{"lastDate":"10/05/2021","predictedDate":"10/05/2022"}},{"name":"BANPU","price":"฿10.60","lossChance":"45.9%","linePercentage":"+8.84%","score":3.36,"factorPercentage":"47.40%","advice":"Sell","pe":12.16,"pbv":1.04,"dvdYield":"2.12%","industry":"Resources","sector":"Energy & Utilities","dividend":{"lastDate":"08/09/2021","predictedDate":"08/09/2022"}},{"name":"QH","price":"฿2.28","lossChance":"50.3%","linePercentage":"+128.83%","score":3.32,"factorPercentage":"32.20%","advice":"Strong Buy","pe":13.92,"pbv":0.92,"dvdYield":"5.26%","industry":"Property & Construction","sector":"Property Development","dividend":{"lastDate":"23/08/2021","predictedDate":"23/08/2022"}},{"name":"BAM","price":"฿21.50","lossChance":"50.3%","linePercentage":"+186.93%","score":3.26,"factorPercentage":"44.20%","advice":"Buy","pe":29.93,"pbv":1.66,"dvdYield":"2.38%","industry":"Financials","sector":"Finance & Securities","dividend":{"lastDate":"06/05/2021","predictedDate":"06/05/2022"}},{"name":"MAJOR","price":"฿20.50","lossChance":"50.3%","linePercentage":"+100.00%","score":3.21,"factorPercentage":"35.60%","advice":"Buy","pe":10.14,"pbv":2.3,"dvdYield":"N.A.%","industry":"Services","sector":"Media & Publishing","dividend":{"lastDate":"25/11/2021","predictedDate":"25/11/2022"}},{"name":"WHA","price":"฿3.56","lossChance":"50.3%","linePercentage":"+183.78%","score":3.17,"factorPercentage":"35.60%","advice":"Strong Buy","pe":26.48,"pbv":1.84,"dvdYield":"2.81%","industry":"Property & Construction","sector":"Property Development","dividend":{"lastDate":"25/11/2021","predictedDate":"25/11/2022"}},{"name":"TASCO","price":"฿18.20","lossChance":"43.3%","linePercentage":"-32.45%","score":3.12,"factorPercentage":"52.40%","advice":"Buy","pe":11.67,"pbv":1.91,"dvdYield":"8.79%","industry":"Property & Construction","sector":"Construction Materials","dividend":{"lastDate":"24/08/2021","predictedDate":"24/08/2022"}},{"name":"BEM","price":"฿8.55","lossChance":"50.3%","linePercentage":"+726.85%","score":3.12,"factorPercentage":"27.20%","advice":"Buy","pe":110.4,"pbv":3.45,"dvdYield":"1.17%","industry":"Services","sector":"Transportation & Logistics","dividend":{"lastDate":"07/05/2021","predictedDate":"07/05/2022"}},{"name":"CRC","price":"฿32.50","lossChance":"52.7%","linePercentage":"+1,000%","score":2.98,"factorPercentage":"27.80%","advice":"Sell","pe":"","pbv":3.55,"dvdYield":"1.23%","industry":"Services","sector":"Commerce","dividend":{"lastDate":"29/04/2021","predictedDate":"29/04/2022"}},{"name":"TTA","price":"฿10.10","lossChance":"44.8%","linePercentage":"-57.18%","score":2.97,"factorPercentage":"50.00%","advice":"Buy","pe":7.53,"pbv":0.92,"dvdYield":"0.20%","industry":"Services","sector":"Transportation & Logistics","dividend":{"lastDate":"25/03/2021","predictedDate":"25/03/2022"}},{"name":"TRUE","price":"฿4.72","lossChance":"46.6%","linePercentage":"-10.74%","score":2.88,"factorPercentage":"29.80%","advice":"Buy","pe":"","pbv":1.93,"dvdYield":"1.48%","industry":"Technology","sector":"Information & Communication Technology","dividend":{"lastDate":"12/03/2021","predictedDate":"12/03/2022"}},{"name":"DTAC","price":"฿45.75","lossChance":"52.7%","linePercentage":"+365.33%","score":2.83,"factorPercentage":"31.00%","advice":"Buy","pe":31.26,"pbv":5.42,"dvdYield":"6.54%","industry":"Technology","sector":"Information & Communication Technology","dividend":{"lastDate":"30/07/2021","predictedDate":"30/07/2022"}},{"name":"BEC","price":"฿14.20","lossChance":"52.7%","linePercentage":"+649.34%","score":2.77,"factorPercentage":"44.20%","advice":"Buy","pe":38.7,"pbv":4.82,"dvdYield":"N.A.%","industry":"Services","sector":"Media & Publishing","dividend":{"lastDate":"22/08/2017","predictedDate":"22/08/2018"}},{"name":"PTTGC","price":"฿59.50","lossChance":"46.6%","linePercentage":"-14.89%","score":2.69,"factorPercentage":"54.20%","advice":"Buy","pe":5.57,"pbv":0.86,"dvdYield":"1.67%","industry":"Industrials","sector":"Petrochemicals & Chemicals","dividend":{"lastDate":"03/09/2021","predictedDate":"03/09/2022"}},{"name":"BCP","price":"฿25.50","lossChance":"44.8%","linePercentage":"-30.64%","score":2.65,"factorPercentage":"43.20%","advice":"Buy","pe":5.66,"pbv":0.66,"dvdYield":"1.57%","industry":"Resources","sector":"Energy & Utilities","dividend":{"lastDate":"08/09/2021","predictedDate":"08/09/2022"}},{"name":"CENTEL","price":"฿31.75","lossChance":"52.7%","linePercentage":"+1,000%","score":2.61,"factorPercentage":"28.80%","advice":"Sell","pe":"","pbv":2.38,"dvdYield":"N.A.%","industry":"Services","sector":"Tourism & Leisure","dividend":{"lastDate":"03/05/2019","predictedDate":"03/05/2020"}},{"name":"SIRI","price":"฿1.28","lossChance":"48.3%","linePercentage":"+13.89%","score":2.47,"factorPercentage":"29.20%","advice":"Strong Buy","pe":8.42,"pbv":0.49,"dvdYield":"3.12%","industry":"Property & Construction","sector":"Property Development","dividend":{"lastDate":"15/03/2021","predictedDate":"15/03/2022"}},{"name":"MINT","price":"฿29.75","lossChance":"52.7%","linePercentage":"+445.28%","score":2.33,"factorPercentage":"26.60%","advice":"Buy","pe":"","pbv":2.87,"dvdYield":"N.A.%","industry":"Agro & Food Industry","sector":"Food & Beverage","dividend":{"lastDate":"26/04/2019","predictedDate":"26/04/2020"}},{"name":"BTS","price":"฿9.45","lossChance":"52.7%","linePercentage":"+87.49%","score":2.13,"factorPercentage":"27.20%","advice":"Buy","pe":23.35,"pbv":2.08,"dvdYield":"3.28%","industry":"Services","sector":"Transportation & Logistics","dividend":{"lastDate":"23/07/2021","predictedDate":"23/07/2022"}},{"name":"IRPC","price":"฿3.90","lossChance":"46.8%","linePercentage":"-24.16%","score":1.9,"factorPercentage":"45.80%","advice":"Buy","pe":5.73,"pbv":0.94,"dvdYield":"1.54%","industry":"Resources","sector":"Energy & Utilities","dividend":{"lastDate":"07/09/2021","predictedDate":"07/09/2022"}},{"name":"SPRC","price":"฿9.85","lossChance":"49.5%","linePercentage":"+31.14%","score":1.89,"factorPercentage":"46.80%","advice":"Buy","pe":11.38,"pbv":1.29,"dvdYield":"N.A.%","industry":"Resources","sector":"Energy & Utilities","dividend":{"lastDate":"05/03/2020","predictedDate":"05/03/2021"}},{"name":"CK","price":"฿23.00","lossChance":"56.1%","linePercentage":"+511.97%","score":1.68,"factorPercentage":"20.40%","advice":"Buy","pe":55.37,"pbv":1.47,"dvdYield":"0.87%","industry":"Property & Construction","sector":"Construction Services","dividend":{"lastDate":"10/05/2021","predictedDate":"10/05/2022"}},{"name":"ESSO","price":"฿7.35","lossChance":"46.8%","linePercentage":"-26.19%","score":1.47,"factorPercentage":"45.40%","advice":"Sell","pe":6.16,"pbv":1.4,"dvdYield":"N.A.%","industry":"Resources","sector":"Energy & Utilities","dividend":{"lastDate":"02/05/2019","predictedDate":"02/05/2020"}},{"name":"AOT","price":"฿61.75","lossChance":"56.1%","linePercentage":"+100.00%","score":1.25,"factorPercentage":"23.20%","advice":"Buy","pe":"","pbv":7.85,"dvdYield":"N.A.%","industry":"Services","sector":"Transportation & Logistics","dividend":{"lastDate":"08/12/2020","predictedDate":"08/12/2021"}},{"name":"TOP","price":"฿50.00","lossChance":"56.1%","linePercentage":"+56.45%","score":1.18,"factorPercentage":"37.40%","advice":"Buy","pe":6.89,"pbv":0.88,"dvdYield":"1.40%","industry":"Resources","sector":"Energy & Utilities","dividend":{"lastDate":"09/09/2021","predictedDate":"09/09/2022"}},{"name":"AWC","price":"฿4.82","lossChance":"58.4%","linePercentage":"+100.00%","score":0.94,"factorPercentage":"17.00%","advice":"Strong Buy","pe":"","pbv":1.97,"dvdYield":"N.A.%","industry":"Property & Construction","sector":"Property Development","dividend":{"lastDate":"15/04/2020","predictedDate":"15/04/2021"}}]}